{"WorldStates": [{"Timestamp": "2018-03-30 17:55:07", "Chat": ["<Builder> Mission has started."], "ScreenshotPath": "0-Builder-chat.png"}, {"BuilderGridAbsolute": [], "XPos": 0.0, "TimeAlive": 146, "ZPos": 0.0, "Timestamp": "2018-03-30 17:55:07", "Yaw": -0.7500002, "YPos": 1.0, "BuilderGridRelative": [], "DistanceTravelled": 0, "BuilderInventory": [{"Index": 0, "Type": "cwc_minecraft_red_rn", "Quantity": 20}, {"Index": 1, "Type": "cwc_minecraft_orange_rn", "Quantity": 20}, {"Index": 2, "Type": "cwc_minecraft_yellow_rn", "Quantity": 20}, {"Index": 3, "Type": "cwc_minecraft_green_rn", "Quantity": 20}, {"Index": 4, "Type": "cwc_minecraft_blue_rn", "Quantity": 20}, {"Index": 5, "Type": "cwc_minecraft_purple_rn", "Quantity": 20}], "Pitch": 43.5}, {"Timestamp": "2018-03-30 17:55:21", "Chat": ["<Builder> hello. what are we building this time?"], "ScreenshotPath": "13796-Builder-chat.png"}, {"BuilderGridAbsolute": [], "XPos": 0.0, "TimeAlive": 422, "ZPos": 0.0, "Timestamp": "2018-03-30 17:55:21", "Yaw": -0.7500002, "YPos": 1.0, "BuilderGridRelative": [], "DistanceTravelled": 0, "BuilderInventory": [{"Index": 0, "Type": "cwc_minecraft_red_rn", "Quantity": 20}, {"Index": 1, "Type": "cwc_minecraft_orange_rn", "Quantity": 20}, {"Index": 2, "Type": "cwc_minecraft_yellow_rn", "Quantity": 20}, {"Index": 3, "Type": "cwc_minecraft_green_rn", "Quantity": 20}, {"Index": 4, "Type": "cwc_minecraft_blue_rn", "Quantity": 20}, {"Index": 5, "Type": "cwc_minecraft_purple_rn", "Quantity": 20}], "Pitch": 43.5}, {"Timestamp": "2018-03-30 17:55:36", "Chat": ["<Architect> hello builder, one moment"], "ScreenshotPath": "28660-Builder-chat.png"}, {"BuilderGridAbsolute": [], "XPos": 0.6613617136445877, "TimeAlive": 719, "ZPos": -4.2820605073976035, "Timestamp": "2018-03-30 17:55:36", "Yaw": 3.2999935, "YPos": 1.0, "BuilderGridRelative": [], "DistanceTravelled": 517, "BuilderInventory": [{"Index": 0, "Type": "cwc_minecraft_red_rn", "Quantity": 20}, {"Index": 1, "Type": "cwc_minecraft_orange_rn", "Quantity": 20}, {"Index": 2, "Type": "cwc_minecraft_yellow_rn", "Quantity": 20}, {"Index": 3, "Type": "cwc_minecraft_green_rn", "Quantity": 20}, {"Index": 4, "Type": "cwc_minecraft_blue_rn", "Quantity": 20}, {"Index": 5, "Type": "cwc_minecraft_purple_rn", "Quantity": 20}], "Pitch": 39.149994}, {"Timestamp": "2018-03-30 17:56:15", "Chat": ["<Architect> ok, to get started we need to place 4 orange blocks as if they are the corners of a 3x3 square, all of them on the ground"], "ScreenshotPath": "67455-Builder-chat.png"}, {"BuilderGridAbsolute": [], "XPos": 0.6613617136445877, "TimeAlive": 1495, "ZPos": -4.2820605073976035, "Timestamp": "2018-03-30 17:56:15", "Yaw": -0.75000674, "YPos": 1.0, "BuilderGridRelative": [], "DistanceTravelled": 517, "BuilderInventory": [{"Index": 0, "Type": "cwc_minecraft_red_rn", "Quantity": 20}, {"Index": 1, "Type": "cwc_minecraft_orange_rn", "Quantity": 20}, {"Index": 2, "Type": "cwc_minecraft_yellow_rn", "Quantity": 20}, {"Index": 3, "Type": "cwc_minecraft_green_rn", "Quantity": 20}, {"Index": 4, "Type": "cwc_minecraft_blue_rn", "Quantity": 20}, {"Index": 5, "Type": "cwc_minecraft_purple_rn", "Quantity": 20}], "Pitch": 37.649986}, {"Timestamp": "2018-03-30 17:56:29", "Chat": ["<Builder> can i put them anywhere?"]}, {"BuilderGridAbsolute": [], "XPos": 0.6613617136445877, "TimeAlive": 1784, "ZPos": -4.2820605073976035, "Timestamp": "2018-03-30 17:56:29", "Yaw": -0.75000674, "YPos": 1.0, "ScreenshotPath": "81918-Builder-chat.png", "BuilderGridRelative": [], "DistanceTravelled": 517, "BuilderInventory": [{"Index": 0, "Type": "cwc_minecraft_red_rn", "Quantity": 20}, {"Index": 1, "Type": "cwc_minecraft_orange_rn", "Quantity": 20}, {"Index": 2, "Type": "cwc_minecraft_yellow_rn", "Quantity": 20}, {"Index": 3, "Type": "cwc_minecraft_green_rn", "Quantity": 20}, {"Index": 4, "Type": "cwc_minecraft_blue_rn", "Quantity": 20}, {"Index": 5, "Type": "cwc_minecraft_purple_rn", "Quantity": 20}], "Pitch": 37.649986}, {"BuilderGridAbsolute": [{"Y": 1, "X": -5, "Z": -3, "Type": "cwc_minecraft_orange_rn"}], "XPos": -1.8393560800004702, "TimeAlive": 1903, "ZPos": -3.653545553701453, "Timestamp": "2018-03-30 17:56:35", "Yaw": 68.70001, "YPos": 1.0, "BuilderGridRelative": [{"Y": 0, "X": -3, "Z": 1, "Type": "cwc_minecraft_orange_rn"}], "DistanceTravelled": 776, "BuilderInventory": [{"Index": 0, "Type": "cwc_minecraft_red_rn", "Quantity": 20}, {"Index": 1, "Type": "cwc_minecraft_orange_rn", "Quantity": 19}, {"Index": 2, "Type": "cwc_minecraft_yellow_rn", "Quantity": 20}, {"Index": 3, "Type": "cwc_minecraft_green_rn", "Quantity": 20}, {"Index": 4, "Type": "cwc_minecraft_blue_rn", "Quantity": 20}, {"Index": 5, "Type": "cwc_minecraft_purple_rn", "Quantity": 20}], "Pitch": 33.149986}, {"Timestamp": "2018-03-30 17:56:35", "ScreenshotPath": "87916-Builder-putdown.png"}, {"BuilderGridAbsolute": [{"Y": 1, "X": -5, "Z": -3, "Type": "cwc_minecraft_orange_rn"}, {"Y": 1, "X": -3, "Z": -3, "Type": "cwc_minecraft_orange_rn"}], "XPos": -1.8393560800004702, "TimeAlive": 1972, "ZPos": -3.653545553701453, "Timestamp": "2018-03-30 17:56:38", "Yaw": 36.150013, "YPos": 1.0, "BuilderGridRelative": [{"Y": 0, "X": -3, "Z": 1, "Type": "cwc_minecraft_orange_rn"}, {"Y": 0, "X": -1, "Z": 1, "Type": "cwc_minecraft_orange_rn"}], "DistanceTravelled": 776, "BuilderInventory": [{"Index": 0, "Type": "cwc_minecraft_red_rn", "Quantity": 20}, {"Index": 1, "Type": "cwc_minecraft_orange_rn", "Quantity": 18}, {"Index": 2, "Type": "cwc_minecraft_yellow_rn", "Quantity": 20}, {"Index": 3, "Type": "cwc_minecraft_green_rn", "Quantity": 20}, {"Index": 4, "Type": "cwc_minecraft_blue_rn", "Quantity": 20}, {"Index": 5, "Type": "cwc_minecraft_purple_rn", "Quantity": 20}], "Pitch": 54.899994}, {"Timestamp": "2018-03-30 17:56:38", "ScreenshotPath": "91367-Builder-putdown.png"}, {"BuilderGridAbsolute": [{"Y": 1, "X": -5, "Z": -5, "Type": "cwc_minecraft_orange_rn"}, {"Y": 1, "X": -5, "Z": -3, "Type": "cwc_minecraft_orange_rn"}, {"Y": 1, "X": -3, "Z": -3, "Type": "cwc_minecraft_orange_rn"}], "XPos": -1.8393560800004702, "TimeAlive": 2002, "ZPos": -3.653545553701453, "Timestamp": "2018-03-30 17:56:40", "Yaw": 104.700005, "YPos": 1.0, "BuilderGridRelative": [{"Y": 0, "X": -3, "Z": -1, "Type": "cwc_minecraft_orange_rn"}, {"Y": 0, "X": -3, "Z": 1, "Type": "cwc_minecraft_orange_rn"}, {"Y": 0, "X": -1, "Z": 1, "Type": "cwc_minecraft_orange_rn"}], "DistanceTravelled": 776, "BuilderInventory": [{"Index": 0, "Type": "cwc_minecraft_red_rn", "Quantity": 20}, {"Index": 1, "Type": "cwc_minecraft_orange_rn", "Quantity": 17}, {"Index": 2, "Type": "cwc_minecraft_yellow_rn", "Quantity": 20}, {"Index": 3, "Type": "cwc_minecraft_green_rn", "Quantity": 20}, {"Index": 4, "Type": "cwc_minecraft_blue_rn", "Quantity": 20}, {"Index": 5, "Type": "cwc_minecraft_purple_rn", "Quantity": 20}], "Chat": ["<Architect> yes, the rest of the structure extends upwards"], "Pitch": 30.899988}, {"BuilderGridAbsolute": [{"Y": 1, "X": -5, "Z": -5, "Type": "cwc_minecraft_orange_rn"}, {"Y": 1, "X": -5, "Z": -3, "Type": "cwc_minecraft_orange_rn"}, {"Y": 1, "X": -3, "Z": -3, "Type": "cwc_minecraft_orange_rn"}], "XPos": -1.8393560800004702, "TimeAlive": 2003, "ZPos": -3.653545553701453, "Timestamp": "2018-03-30 17:56:40", "Yaw": 104.700005, "YPos": 1.0, "ScreenshotPath": "93229-Builder-putdown.png", "BuilderGridRelative": [{"Y": 0, "X": -3, "Z": -1, "Type": "cwc_minecraft_orange_rn"}, {"Y": 0, "X": -3, "Z": 1, "Type": "cwc_minecraft_orange_rn"}, {"Y": 0, "X": -1, "Z": 1, "Type": "cwc_minecraft_orange_rn"}], "DistanceTravelled": 776, "BuilderInventory": [{"Index": 0, "Type": "cwc_minecraft_red_rn", "Quantity": 20}, {"Index": 1, "Type": "cwc_minecraft_orange_rn", "Quantity": 17}, {"Index": 2, "Type": "cwc_minecraft_yellow_rn", "Quantity": 20}, {"Index": 3, "Type": "cwc_minecraft_green_rn", "Quantity": 20}, {"Index": 4, "Type": "cwc_minecraft_blue_rn", "Quantity": 20}, {"Index": 5, "Type": "cwc_minecraft_purple_rn", "Quantity": 20}], "Pitch": 30.899988}, {"BuilderGridAbsolute": [{"Y": 1, "X": -5, "Z": -5, "Type": "cwc_minecraft_orange_rn"}, {"Y": 1, "X": -3, "Z": -5, "Type": "cwc_minecraft_orange_rn"}, {"Y": 1, "X": -5, "Z": -3, "Type": "cwc_minecraft_orange_rn"}, {"Y": 1, "X": -3, "Z": -3, "Type": "cwc_minecraft_orange_rn"}], "XPos": -1.5028397856967328, "TimeAlive": 2062, "ZPos": -3.4097942023734165, "Timestamp": "2018-03-30 17:56:43", "Yaw": 132.45001, "YPos": 1.0, "BuilderGridRelative": [{"Y": 0, "X": -3, "Z": -1, "Type": "cwc_minecraft_orange_rn"}, {"Y": 0, "X": -1, "Z": -1, "Type": "cwc_minecraft_orange_rn"}, {"Y": 0, "X": -3, "Z": 1, "Type": "cwc_minecraft_orange_rn"}, {"Y": 0, "X": -1, "Z": 1, "Type": "cwc_minecraft_orange_rn"}], "DistanceTravelled": 818, "BuilderInventory": [{"Index": 0, "Type": "cwc_minecraft_red_rn", "Quantity": 20}, {"Index": 1, "Type": "cwc_minecraft_orange_rn", "Quantity": 16}, {"Index": 2, "Type": "cwc_minecraft_yellow_rn", "Quantity": 20}, {"Index": 3, "Type": "cwc_minecraft_green_rn", "Quantity": 20}, {"Index": 4, "Type": "cwc_minecraft_blue_rn", "Quantity": 20}, {"Index": 5, "Type": "cwc_minecraft_purple_rn", "Quantity": 20}], "Pitch": 51.599976}, {"Timestamp": "2018-03-30 17:56:43", "ScreenshotPath": "95865-Builder-putdown.png"}, {"Timestamp": "2018-03-30 17:56:49", "Chat": ["<Architect> perfect"]}, {"BuilderGridAbsolute": [{"Y": 1, "X": -5, "Z": -5, "Type": "cwc_minecraft_orange_rn"}, {"Y": 1, "X": -3, "Z": -5, "Type": "cwc_minecraft_orange_rn"}, {"Y": 1, "X": -5, "Z": -3, "Type": "cwc_minecraft_orange_rn"}, {"Y": 1, "X": -3, "Z": -3, "Type": "cwc_minecraft_orange_rn"}], "XPos": -6.063515631839836, "TimeAlive": 2186, "ZPos": -3.737408576850836, "Timestamp": "2018-03-30 17:56:49", "Yaw": 273.75, "YPos": 1.0, "ScreenshotPath": "102014-Builder-chat.png", "BuilderGridRelative": [{"Y": 0, "X": 2, "Z": -1, "Type": "cwc_minecraft_orange_rn"}, {"Y": 0, "X": 4, "Z": -1, "Type": "cwc_minecraft_orange_rn"}, {"Y": 0, "X": 2, "Z": 1, "Type": "cwc_minecraft_orange_rn"}, {"Y": 0, "X": 4, "Z": 1, "Type": "cwc_minecraft_orange_rn"}], "DistanceTravelled": 1890, "BuilderInventory": [{"Index": 0, "Type": "cwc_minecraft_red_rn", "Quantity": 20}, {"Index": 1, "Type": "cwc_minecraft_orange_rn", "Quantity": 16}, {"Index": 2, "Type": "cwc_minecraft_yellow_rn", "Quantity": 20}, {"Index": 3, "Type": "cwc_minecraft_green_rn", "Quantity": 20}, {"Index": 4, "Type": "cwc_minecraft_blue_rn", "Quantity": 20}, {"Index": 5, "Type": "cwc_minecraft_purple_rn", "Quantity": 20}], "Pitch": 32.69998}, {"Timestamp": "2018-03-30 17:56:57", "Chat": ["<Architect> one moment while i look at the structure"]}, {"Timestamp": "2018-03-30 17:56:57", "ScreenshotPath": "109964-Builder-chat.png"}, {"BuilderGridAbsolute": [{"Y": 1, "X": -5, "Z": -5, "Type": "cwc_minecraft_orange_rn"}, {"Y": 1, "X": -3, "Z": -5, "Type": "cwc_minecraft_orange_rn"}, {"Y": 1, "X": -5, "Z": -3, "Type": "cwc_minecraft_orange_rn"}, {"Y": 1, "X": -3, "Z": -3, "Type": "cwc_minecraft_orange_rn"}], "XPos": -6.063515631839836, "TimeAlive": 2345, "ZPos": -3.737408576850836, "Timestamp": "2018-03-30 17:56:57", "Yaw": 273.75, "YPos": 1.0, "BuilderGridRelative": [{"Y": 0, "X": 2, "Z": -1, "Type": "cwc_minecraft_orange_rn"}, {"Y": 0, "X": 4, "Z": -1, "Type": "cwc_minecraft_orange_rn"}, {"Y": 0, "X": 2, "Z": 1, "Type": "cwc_minecraft_orange_rn"}, {"Y": 0, "X": 4, "Z": 1, "Type": "cwc_minecraft_orange_rn"}], "DistanceTravelled": 1890, "BuilderInventory": [{"Index": 0, "Type": "cwc_minecraft_red_rn", "Quantity": 20}, {"Index": 1, "Type": "cwc_minecraft_orange_rn", "Quantity": 16}, {"Index": 2, "Type": "cwc_minecraft_yellow_rn", "Quantity": 20}, {"Index": 3, "Type": "cwc_minecraft_green_rn", "Quantity": 20}, {"Index": 4, "Type": "cwc_minecraft_blue_rn", "Quantity": 20}, {"Index": 5, "Type": "cwc_minecraft_purple_rn", "Quantity": 20}], "Pitch": 32.69998}, {"Timestamp": "2018-03-30 17:57:38", "Chat": ["<Architect> the second level of the structure consists wholly of red blocks. start by putting a red block on each orange block"], "ScreenshotPath": "150457-Builder-chat.png"}, {"BuilderGridAbsolute": [{"Y": 1, "X": -5, "Z": -5, "Type": "cwc_minecraft_orange_rn"}, {"Y": 1, "X": -3, "Z": -5, "Type": "cwc_minecraft_orange_rn"}, {"Y": 1, "X": -5, "Z": -3, "Type": "cwc_minecraft_orange_rn"}, {"Y": 1, "X": -3, "Z": -3, "Type": "cwc_minecraft_orange_rn"}], "XPos": -6.063515631839836, "TimeAlive": 3155, "ZPos": -3.737408576850836, "Timestamp": "2018-03-30 17:57:38", "Yaw": 273.6, "YPos": 1.0, "BuilderGridRelative": [{"Y": 0, "X": 2, "Z": -1, "Type": "cwc_minecraft_orange_rn"}, {"Y": 0, "X": 4, "Z": -1, "Type": "cwc_minecraft_orange_rn"}, {"Y": 0, "X": 2, "Z": 1, "Type": "cwc_minecraft_orange_rn"}, {"Y": 0, "X": 4, "Z": 1, "Type": "cwc_minecraft_orange_rn"}], "DistanceTravelled": 1890, "BuilderInventory": [{"Index": 0, "Type": "cwc_minecraft_red_rn", "Quantity": 20}, {"Index": 1, "Type": "cwc_minecraft_orange_rn", "Quantity": 16}, {"Index": 2, "Type": "cwc_minecraft_yellow_rn", "Quantity": 20}, {"Index": 3, "Type": "cwc_minecraft_green_rn", "Quantity": 20}, {"Index": 4, "Type": "cwc_minecraft_blue_rn", "Quantity": 20}, {"Index": 5, "Type": "cwc_minecraft_purple_rn", "Quantity": 20}], "Pitch": 32.69998}, {"BuilderGridAbsolute": [{"Y": 1, "X": -5, "Z": -5, "Type": "cwc_minecraft_orange_rn"}, {"Y": 1, "X": -3, "Z": -5, "Type": "cwc_minecraft_orange_rn"}, {"Y": 1, "X": -5, "Z": -3, "Type": "cwc_minecraft_orange_rn"}, {"Y": 1, "X": -3, "Z": -3, "Type": "cwc_minecraft_orange_rn"}, {"Y": 2, "X": -5, "Z": -5, "Type": "cwc_minecraft_red_rn"}], "XPos": -6.063515631839836, "TimeAlive": 3286, "ZPos": -3.737408576850836, "Timestamp": "2018-03-30 17:57:44", "Yaw": 244.95001, "YPos": 1.0, "ScreenshotPath": "157056-Builder-putdown.png", "BuilderGridRelative": [{"Y": 0, "X": 2, "Z": -1, "Type": "cwc_minecraft_orange_rn"}, {"Y": 0, "X": 4, "Z": -1, "Type": "cwc_minecraft_orange_rn"}, {"Y": 0, "X": 2, "Z": 1, "Type": "cwc_minecraft_orange_rn"}, {"Y": 0, "X": 4, "Z": 1, "Type": "cwc_minecraft_orange_rn"}, {"Y": 1, "X": 2, "Z": -1, "Type": "cwc_minecraft_red_rn"}], "DistanceTravelled": 1890, "BuilderInventory": [{"Index": 0, "Type": "cwc_minecraft_red_rn", "Quantity": 19}, {"Index": 1, "Type": "cwc_minecraft_orange_rn", "Quantity": 16}, {"Index": 2, "Type": "cwc_minecraft_yellow_rn", "Quantity": 20}, {"Index": 3, "Type": "cwc_minecraft_green_rn", "Quantity": 20}, {"Index": 4, "Type": "cwc_minecraft_blue_rn", "Quantity": 20}, {"Index": 5, "Type": "cwc_minecraft_purple_rn", "Quantity": 20}], "Pitch": 19.349981}, {"BuilderGridAbsolute": [{"Y": 1, "X": -5, "Z": -5, "Type": "cwc_minecraft_orange_rn"}, {"Y": 1, "X": -3, "Z": -5, "Type": "cwc_minecraft_orange_rn"}, {"Y": 1, "X": -5, "Z": -3, "Type": "cwc_minecraft_orange_rn"}, {"Y": 1, "X": -3, "Z": -3, "Type": "cwc_minecraft_orange_rn"}, {"Y": 2, "X": -5, "Z": -5, "Type": "cwc_minecraft_red_rn"}, {"Y": 2, "X": -5, "Z": -3, "Type": "cwc_minecraft_red_rn"}], "XPos": -6.072447814665432, "TimeAlive": 3314, "ZPos": -1.9295058852641986, "Timestamp": "2018-03-30 17:57:45", "Yaw": 251.55002, "YPos": 1.0, "ScreenshotPath": "158455-Builder-putdown.png", "BuilderGridRelative": [{"Y": 0, "X": 2, "Z": -3, "Type": "cwc_minecraft_orange_rn"}, {"Y": 0, "X": 4, "Z": -3, "Type": "cwc_minecraft_orange_rn"}, {"Y": 0, "X": 2, "Z": -1, "Type": "cwc_minecraft_orange_rn"}, {"Y": 0, "X": 4, "Z": -1, "Type": "cwc_minecraft_orange_rn"}, {"Y": 1, "X": 2, "Z": -3, "Type": "cwc_minecraft_red_rn"}, {"Y": 1, "X": 2, "Z": -1, "Type": "cwc_minecraft_red_rn"}], "DistanceTravelled": 2100, "BuilderInventory": [{"Index": 0, "Type": "cwc_minecraft_red_rn", "Quantity": 18}, {"Index": 1, "Type": "cwc_minecraft_orange_rn", "Quantity": 16}, {"Index": 2, "Type": "cwc_minecraft_yellow_rn", "Quantity": 20}, {"Index": 3, "Type": "cwc_minecraft_green_rn", "Quantity": 20}, {"Index": 4, "Type": "cwc_minecraft_blue_rn", "Quantity": 20}, {"Index": 5, "Type": "cwc_minecraft_purple_rn", "Quantity": 20}], "Pitch": 21.749983}, {"BuilderGridAbsolute": [{"Y": 1, "X": -5, "Z": -5, "Type": "cwc_minecraft_orange_rn"}, {"Y": 1, "X": -3, "Z": -5, "Type": "cwc_minecraft_orange_rn"}, {"Y": 1, "X": -5, "Z": -3, "Type": "cwc_minecraft_orange_rn"}, {"Y": 1, "X": -3, "Z": -3, "Type": "cwc_minecraft_orange_rn"}, {"Y": 2, "X": -5, "Z": -5, "Type": "cwc_minecraft_red_rn"}, {"Y": 2, "X": -5, "Z": -3, "Type": "cwc_minecraft_red_rn"}, {"Y": 2, "X": -3, "Z": -3, "Type": "cwc_minecraft_red_rn"}], "XPos": -2.306735124167307, "TimeAlive": 3370, "ZPos": -0.8667956669232741, "Timestamp": "2018-03-30 17:57:49", "Yaw": 175.50012, "YPos": 2.7908794834281845, "ScreenshotPath": "161255-Builder-putdown.png", "BuilderGridRelative": [{"Y": -1, "X": -2, "Z": -4, "Type": "cwc_minecraft_orange_rn"}, {"Y": -1, "X": 0, "Z": -4, "Type": "cwc_minecraft_orange_rn"}, {"Y": -1, "X": -2, "Z": -2, "Type": "cwc_minecraft_orange_rn"}, {"Y": -1, "X": 0, "Z": -2, "Type": "cwc_minecraft_orange_rn"}, {"Y": 0, "X": -2, "Z": -4, "Type": "cwc_minecraft_red_rn"}, {"Y": 0, "X": -2, "Z": -2, "Type": "cwc_minecraft_red_rn"}, {"Y": 0, "X": 0, "Z": -2, "Type": "cwc_minecraft_red_rn"}], "DistanceTravelled": 2440, "BuilderInventory": [{"Index": 0, "Type": "cwc_minecraft_red_rn", "Quantity": 17}, {"Index": 1, "Type": "cwc_minecraft_orange_rn", "Quantity": 16}, {"Index": 2, "Type": "cwc_minecraft_yellow_rn", "Quantity": 20}, {"Index": 3, "Type": "cwc_minecraft_green_rn", "Quantity": 20}, {"Index": 4, "Type": "cwc_minecraft_blue_rn", "Quantity": 20}, {"Index": 5, "Type": "cwc_minecraft_purple_rn", "Quantity": 20}], "Pitch": 57.0}, {"BuilderGridAbsolute": [{"Y": 1, "X": -5, "Z": -5, "Type": "cwc_minecraft_orange_rn"}, {"Y": 1, "X": -3, "Z": -5, "Type": "cwc_minecraft_orange_rn"}, {"Y": 1, "X": -5, "Z": -3, "Type": "cwc_minecraft_orange_rn"}, {"Y": 1, "X": -3, "Z": -3, "Type": "cwc_minecraft_orange_rn"}, {"Y": 2, "X": -5, "Z": -5, "Type": "cwc_minecraft_red_rn"}, {"Y": 2, "X": -3, "Z": -5, "Type": "cwc_minecraft_red_rn"}, {"Y": 2, "X": -5, "Z": -3, "Type": "cwc_minecraft_red_rn"}, {"Y": 2, "X": -3, "Z": -3, "Type": "cwc_minecraft_red_rn"}], "XPos": -1.1759742404625497, "TimeAlive": 3427, "ZPos": -4.48149556039088, "Timestamp": "2018-03-30 17:57:51", "Yaw": 87.00012, "YPos": 2.8086870427730335, "ScreenshotPath": "164104-Builder-putdown.png", "BuilderGridRelative": [{"Y": -1, "X": -3, "Z": 0, "Type": "cwc_minecraft_orange_rn"}, {"Y": -1, "X": -1, "Z": 0, "Type": "cwc_minecraft_orange_rn"}, {"Y": -1, "X": -3, "Z": 2, "Type": "cwc_minecraft_orange_rn"}, {"Y": -1, "X": -1, "Z": 2, "Type": "cwc_minecraft_orange_rn"}, {"Y": 0, "X": -3, "Z": 0, "Type": "cwc_minecraft_red_rn"}, {"Y": 0, "X": -1, "Z": 0, "Type": "cwc_minecraft_red_rn"}, {"Y": 0, "X": -3, "Z": 2, "Type": "cwc_minecraft_red_rn"}, {"Y": 0, "X": -1, "Z": 2, "Type": "cwc_minecraft_red_rn"}], "DistanceTravelled": 2440, "BuilderInventory": [{"Index": 0, "Type": "cwc_minecraft_red_rn", "Quantity": 16}, {"Index": 1, "Type": "cwc_minecraft_orange_rn", "Quantity": 16}, {"Index": 2, "Type": "cwc_minecraft_yellow_rn", "Quantity": 20}, {"Index": 3, "Type": "cwc_minecraft_green_rn", "Quantity": 20}, {"Index": 4, "Type": "cwc_minecraft_blue_rn", "Quantity": 20}, {"Index": 5, "Type": "cwc_minecraft_purple_rn", "Quantity": 20}], "Pitch": 57.599983}, {"Timestamp": "2018-03-30 17:58:19", "Chat": ["<Architect> good, now please fill in the outer sides of the second level 3x3 square but leave the middle open"]}, {"BuilderGridAbsolute": [{"Y": 1, "X": -5, "Z": -5, "Type": "cwc_minecraft_orange_rn"}, {"Y": 1, "X": -3, "Z": -5, "Type": "cwc_minecraft_orange_rn"}, {"Y": 1, "X": -5, "Z": -3, "Type": "cwc_minecraft_orange_rn"}, {"Y": 1, "X": -3, "Z": -3, "Type": "cwc_minecraft_orange_rn"}, {"Y": 2, "X": -5, "Z": -5, "Type": "cwc_minecraft_red_rn"}, {"Y": 2, "X": -3, "Z": -5, "Type": "cwc_minecraft_red_rn"}, {"Y": 2, "X": -5, "Z": -3, "Type": "cwc_minecraft_red_rn"}, {"Y": 2, "X": -3, "Z": -3, "Type": "cwc_minecraft_red_rn"}], "XPos": -3.6005294957124883, "TimeAlive": 3987, "ZPos": -0.8839172416472134, "Timestamp": "2018-03-30 17:58:19", "Yaw": 180.0001, "YPos": 2.8086870427730335, "ScreenshotPath": "192068-Builder-chat.png", "BuilderGridRelative": [{"Y": -1, "X": -1, "Z": -4, "Type": "cwc_minecraft_orange_rn"}, {"Y": -1, "X": 1, "Z": -4, "Type": "cwc_minecraft_orange_rn"}, {"Y": -1, "X": -1, "Z": -2, "Type": "cwc_minecraft_orange_rn"}, {"Y": -1, "X": 1, "Z": -2, "Type": "cwc_minecraft_orange_rn"}, {"Y": 0, "X": -1, "Z": -4, "Type": "cwc_minecraft_red_rn"}, {"Y": 0, "X": 1, "Z": -4, "Type": "cwc_minecraft_red_rn"}, {"Y": 0, "X": -1, "Z": -2, "Type": "cwc_minecraft_red_rn"}, {"Y": 0, "X": 1, "Z": -2, "Type": "cwc_minecraft_red_rn"}], "DistanceTravelled": 2440, "BuilderInventory": [{"Index": 0, "Type": "cwc_minecraft_red_rn", "Quantity": 16}, {"Index": 1, "Type": "cwc_minecraft_orange_rn", "Quantity": 16}, {"Index": 2, "Type": "cwc_minecraft_yellow_rn", "Quantity": 20}, {"Index": 3, "Type": "cwc_minecraft_green_rn", "Quantity": 20}, {"Index": 4, "Type": "cwc_minecraft_blue_rn", "Quantity": 20}, {"Index": 5, "Type": "cwc_minecraft_purple_rn", "Quantity": 20}], "Pitch": 43.199993}, {"Timestamp": "2018-03-30 17:58:28", "Chat": ["<Architect> using red blocks"]}, {"BuilderGridAbsolute": [{"Y": 1, "X": -5, "Z": -5, "Type": "cwc_minecraft_orange_rn"}, {"Y": 1, "X": -3, "Z": -5, "Type": "cwc_minecraft_orange_rn"}, {"Y": 1, "X": -5, "Z": -3, "Type": "cwc_minecraft_orange_rn"}, {"Y": 1, "X": -3, "Z": -3, "Type": "cwc_minecraft_orange_rn"}, {"Y": 2, "X": -5, "Z": -5, "Type": "cwc_minecraft_red_rn"}, {"Y": 2, "X": -3, "Z": -5, "Type": "cwc_minecraft_red_rn"}, {"Y": 2, "X": -5, "Z": -3, "Type": "cwc_minecraft_red_rn"}, {"Y": 2, "X": -3, "Z": -3, "Type": "cwc_minecraft_red_rn"}], "XPos": -3.6005294957124883, "TimeAlive": 4164, "ZPos": -0.8839172416472134, "Timestamp": "2018-03-30 17:58:28", "Yaw": 180.0001, "YPos": 2.8086870427730335, "ScreenshotPath": "200915-Builder-chat.png", "BuilderGridRelative": [{"Y": -1, "X": -1, "Z": -4, "Type": "cwc_minecraft_orange_rn"}, {"Y": -1, "X": 1, "Z": -4, "Type": "cwc_minecraft_orange_rn"}, {"Y": -1, "X": -1, "Z": -2, "Type": "cwc_minecraft_orange_rn"}, {"Y": -1, "X": 1, "Z": -2, "Type": "cwc_minecraft_orange_rn"}, {"Y": 0, "X": -1, "Z": -4, "Type": "cwc_minecraft_red_rn"}, {"Y": 0, "X": 1, "Z": -4, "Type": "cwc_minecraft_red_rn"}, {"Y": 0, "X": -1, "Z": -2, "Type": "cwc_minecraft_red_rn"}, {"Y": 0, "X": 1, "Z": -2, "Type": "cwc_minecraft_red_rn"}], "DistanceTravelled": 2440, "BuilderInventory": [{"Index": 0, "Type": "cwc_minecraft_red_rn", "Quantity": 16}, {"Index": 1, "Type": "cwc_minecraft_orange_rn", "Quantity": 16}, {"Index": 2, "Type": "cwc_minecraft_yellow_rn", "Quantity": 20}, {"Index": 3, "Type": "cwc_minecraft_green_rn", "Quantity": 20}, {"Index": 4, "Type": "cwc_minecraft_blue_rn", "Quantity": 20}, {"Index": 5, "Type": "cwc_minecraft_purple_rn", "Quantity": 20}], "Pitch": 43.199993}, {"Timestamp": "2018-03-30 17:58:31", "Chat": ["<Builder> okay"]}, {"BuilderGridAbsolute": [{"Y": 1, "X": -5, "Z": -5, "Type": "cwc_minecraft_orange_rn"}, {"Y": 1, "X": -3, "Z": -5, "Type": "cwc_minecraft_orange_rn"}, {"Y": 1, "X": -5, "Z": -3, "Type": "cwc_minecraft_orange_rn"}, {"Y": 1, "X": -3, "Z": -3, "Type": "cwc_minecraft_orange_rn"}, {"Y": 2, "X": -5, "Z": -5, "Type": "cwc_minecraft_red_rn"}, {"Y": 2, "X": -3, "Z": -5, "Type": "cwc_minecraft_red_rn"}, {"Y": 2, "X": -5, "Z": -3, "Type": "cwc_minecraft_red_rn"}, {"Y": 2, "X": -3, "Z": -3, "Type": "cwc_minecraft_red_rn"}], "XPos": -3.6005294957124883, "TimeAlive": 4224, "ZPos": -0.8839172416472134, "Timestamp": "2018-03-30 17:58:31", "Yaw": 180.0001, "YPos": 2.8086870427730335, "ScreenshotPath": "203914-Builder-chat.png", "BuilderGridRelative": [{"Y": -1, "X": -1, "Z": -4, "Type": "cwc_minecraft_orange_rn"}, {"Y": -1, "X": 1, "Z": -4, "Type": "cwc_minecraft_orange_rn"}, {"Y": -1, "X": -1, "Z": -2, "Type": "cwc_minecraft_orange_rn"}, {"Y": -1, "X": 1, "Z": -2, "Type": "cwc_minecraft_orange_rn"}, {"Y": 0, "X": -1, "Z": -4, "Type": "cwc_minecraft_red_rn"}, {"Y": 0, "X": 1, "Z": -4, "Type": "cwc_minecraft_red_rn"}, {"Y": 0, "X": -1, "Z": -2, "Type": "cwc_minecraft_red_rn"}, {"Y": 0, "X": 1, "Z": -2, "Type": "cwc_minecraft_red_rn"}], "DistanceTravelled": 2440, "BuilderInventory": [{"Index": 0, "Type": "cwc_minecraft_red_rn", "Quantity": 16}, {"Index": 1, "Type": "cwc_minecraft_orange_rn", "Quantity": 16}, {"Index": 2, "Type": "cwc_minecraft_yellow_rn", "Quantity": 20}, {"Index": 3, "Type": "cwc_minecraft_green_rn", "Quantity": 20}, {"Index": 4, "Type": "cwc_minecraft_blue_rn", "Quantity": 20}, {"Index": 5, "Type": "cwc_minecraft_purple_rn", "Quantity": 20}], "Pitch": 43.199993}, {"BuilderGridAbsolute": [{"Y": 1, "X": -5, "Z": -5, "Type": "cwc_minecraft_orange_rn"}, {"Y": 1, "X": -3, "Z": -5, "Type": "cwc_minecraft_orange_rn"}, {"Y": 1, "X": -5, "Z": -3, "Type": "cwc_minecraft_orange_rn"}, {"Y": 1, "X": -3, "Z": -3, "Type": "cwc_minecraft_orange_rn"}, {"Y": 2, "X": -5, "Z": -5, "Type": "cwc_minecraft_red_rn"}, {"Y": 2, "X": -3, "Z": -5, "Type": "cwc_minecraft_red_rn"}, {"Y": 2, "X": -3, "Z": -4, "Type": "cwc_minecraft_red_rn"}, {"Y": 2, "X": -5, "Z": -3, "Type": "cwc_minecraft_red_rn"}, {"Y": 2, "X": -3, "Z": -3, "Type": "cwc_minecraft_red_rn"}], "XPos": -1.5200411419662894, "TimeAlive": 4290, "ZPos": -2.4588484313025245, "Timestamp": "2018-03-30 17:58:35", "Yaw": 137.25008, "YPos": 2.8086870427730335, "ScreenshotPath": "207265-Builder-putdown.png", "BuilderGridRelative": [{"Y": -1, "X": -3, "Z": -2, "Type": "cwc_minecraft_orange_rn"}, {"Y": -1, "X": -1, "Z": -2, "Type": "cwc_minecraft_orange_rn"}, {"Y": -1, "X": -3, "Z": 0, "Type": "cwc_minecraft_orange_rn"}, {"Y": -1, "X": -1, "Z": 0, "Type": "cwc_minecraft_orange_rn"}, {"Y": 0, "X": -3, "Z": -2, "Type": "cwc_minecraft_red_rn"}, {"Y": 0, "X": -1, "Z": -2, "Type": "cwc_minecraft_red_rn"}, {"Y": 0, "X": -1, "Z": -1, "Type": "cwc_minecraft_red_rn"}, {"Y": 0, "X": -3, "Z": 0, "Type": "cwc_minecraft_red_rn"}, {"Y": 0, "X": -1, "Z": 0, "Type": "cwc_minecraft_red_rn"}], "DistanceTravelled": 2440, "BuilderInventory": [{"Index": 0, "Type": "cwc_minecraft_red_rn", "Quantity": 15}, {"Index": 1, "Type": "cwc_minecraft_orange_rn", "Quantity": 16}, {"Index": 2, "Type": "cwc_minecraft_yellow_rn", "Quantity": 20}, {"Index": 3, "Type": "cwc_minecraft_green_rn", "Quantity": 20}, {"Index": 4, "Type": "cwc_minecraft_blue_rn", "Quantity": 20}, {"Index": 5, "Type": "cwc_minecraft_purple_rn", "Quantity": 20}], "Pitch": 46.949986}, {"BuilderGridAbsolute": [{"Y": 1, "X": -5, "Z": -5, "Type": "cwc_minecraft_orange_rn"}, {"Y": 1, "X": -3, "Z": -5, "Type": "cwc_minecraft_orange_rn"}, {"Y": 1, "X": -5, "Z": -3, "Type": "cwc_minecraft_orange_rn"}, {"Y": 1, "X": -3, "Z": -3, "Type": "cwc_minecraft_orange_rn"}, {"Y": 2, "X": -5, "Z": -5, "Type": "cwc_minecraft_red_rn"}, {"Y": 2, "X": -3, "Z": -5, "Type": "cwc_minecraft_red_rn"}, {"Y": 2, "X": -3, "Z": -4, "Type": "cwc_minecraft_red_rn"}, {"Y": 2, "X": -5, "Z": -3, "Type": "cwc_minecraft_red_rn"}, {"Y": 2, "X": -4, "Z": -3, "Type": "cwc_minecraft_red_rn"}, {"Y": 2, "X": -3, "Z": -3, "Type": "cwc_minecraft_red_rn"}], "XPos": -1.6999999880790726, "TimeAlive": 4325, "ZPos": -2.4556749198427026, "Timestamp": "2018-03-30 17:58:36", "Yaw": 93.45006, "YPos": 2.8086870427730335, "ScreenshotPath": "209013-Builder-putdown.png", "BuilderGridRelative": [{"Y": -1, "X": -3, "Z": -2, "Type": "cwc_minecraft_orange_rn"}, {"Y": -1, "X": -1, "Z": -2, "Type": "cwc_minecraft_orange_rn"}, {"Y": -1, "X": -3, "Z": 0, "Type": "cwc_minecraft_orange_rn"}, {"Y": -1, "X": -1, "Z": 0, "Type": "cwc_minecraft_orange_rn"}, {"Y": 0, "X": -3, "Z": -2, "Type": "cwc_minecraft_red_rn"}, {"Y": 0, "X": -1, "Z": -2, "Type": "cwc_minecraft_red_rn"}, {"Y": 0, "X": -1, "Z": -1, "Type": "cwc_minecraft_red_rn"}, {"Y": 0, "X": -3, "Z": 0, "Type": "cwc_minecraft_red_rn"}, {"Y": 0, "X": -2, "Z": 0, "Type": "cwc_minecraft_red_rn"}, {"Y": 0, "X": -1, "Z": 0, "Type": "cwc_minecraft_red_rn"}], "DistanceTravelled": 2440, "BuilderInventory": [{"Index": 0, "Type": "cwc_minecraft_red_rn", "Quantity": 14}, {"Index": 1, "Type": "cwc_minecraft_orange_rn", "Quantity": 16}, {"Index": 2, "Type": "cwc_minecraft_yellow_rn", "Quantity": 20}, {"Index": 3, "Type": "cwc_minecraft_green_rn", "Quantity": 20}, {"Index": 4, "Type": "cwc_minecraft_blue_rn", "Quantity": 20}, {"Index": 5, "Type": "cwc_minecraft_purple_rn", "Quantity": 20}], "Pitch": 38.99998}, {"BuilderGridAbsolute": [{"Y": 1, "X": -5, "Z": -5, "Type": "cwc_minecraft_orange_rn"}, {"Y": 1, "X": -3, "Z": -5, "Type": "cwc_minecraft_orange_rn"}, {"Y": 1, "X": -5, "Z": -3, "Type": "cwc_minecraft_orange_rn"}, {"Y": 1, "X": -3, "Z": -3, "Type": "cwc_minecraft_orange_rn"}, {"Y": 2, "X": -5, "Z": -5, "Type": "cwc_minecraft_red_rn"}, {"Y": 2, "X": -4, "Z": -5, "Type": "cwc_minecraft_red_rn"}, {"Y": 2, "X": -3, "Z": -5, "Type": "cwc_minecraft_red_rn"}, {"Y": 2, "X": -3, "Z": -4, "Type": "cwc_minecraft_red_rn"}, {"Y": 2, "X": -5, "Z": -3, "Type": "cwc_minecraft_red_rn"}, {"Y": 2, "X": -4, "Z": -3, "Type": "cwc_minecraft_red_rn"}, {"Y": 2, "X": -3, "Z": -3, "Type": "cwc_minecraft_red_rn"}], "XPos": -1.6999999880790726, "TimeAlive": 4377, "ZPos": -3.5567637742067766, "Timestamp": "2018-03-30 17:58:39", "Yaw": 109.20007, "YPos": 2.8086870427730335, "ScreenshotPath": "211613-Builder-putdown.png", "BuilderGridRelative": [{"Y": -1, "X": -3, "Z": -1, "Type": "cwc_minecraft_orange_rn"}, {"Y": -1, "X": -1, "Z": -1, "Type": "cwc_minecraft_orange_rn"}, {"Y": -1, "X": -3, "Z": 1, "Type": "cwc_minecraft_orange_rn"}, {"Y": -1, "X": -1, "Z": 1, "Type": "cwc_minecraft_orange_rn"}, {"Y": 0, "X": -3, "Z": -1, "Type": "cwc_minecraft_red_rn"}, {"Y": 0, "X": -2, "Z": -1, "Type": "cwc_minecraft_red_rn"}, {"Y": 0, "X": -1, "Z": -1, "Type": "cwc_minecraft_red_rn"}, {"Y": 0, "X": -1, "Z": 0, "Type": "cwc_minecraft_red_rn"}, {"Y": 0, "X": -3, "Z": 1, "Type": "cwc_minecraft_red_rn"}, {"Y": 0, "X": -2, "Z": 1, "Type": "cwc_minecraft_red_rn"}, {"Y": 0, "X": -1, "Z": 1, "Type": "cwc_minecraft_red_rn"}], "DistanceTravelled": 2440, "BuilderInventory": [{"Index": 0, "Type": "cwc_minecraft_red_rn", "Quantity": 13}, {"Index": 1, "Type": "cwc_minecraft_orange_rn", "Quantity": 16}, {"Index": 2, "Type": "cwc_minecraft_yellow_rn", "Quantity": 20}, {"Index": 3, "Type": "cwc_minecraft_green_rn", "Quantity": 20}, {"Index": 4, "Type": "cwc_minecraft_blue_rn", "Quantity": 20}, {"Index": 5, "Type": "cwc_minecraft_purple_rn", "Quantity": 20}], "Pitch": 38.399963}, {"BuilderGridAbsolute": [{"Y": 1, "X": -5, "Z": -5, "Type": "cwc_minecraft_orange_rn"}, {"Y": 1, "X": -3, "Z": -5, "Type": "cwc_minecraft_orange_rn"}, {"Y": 1, "X": -5, "Z": -3, "Type": "cwc_minecraft_orange_rn"}, {"Y": 1, "X": -3, "Z": -3, "Type": "cwc_minecraft_orange_rn"}, {"Y": 2, "X": -5, "Z": -5, "Type": "cwc_minecraft_red_rn"}, {"Y": 2, "X": -4, "Z": -5, "Type": "cwc_minecraft_red_rn"}, {"Y": 2, "X": -3, "Z": -5, "Type": "cwc_minecraft_red_rn"}, {"Y": 2, "X": -5, "Z": -4, "Type": "cwc_minecraft_red_rn"}, {"Y": 2, "X": -3, "Z": -4, "Type": "cwc_minecraft_red_rn"}, {"Y": 2, "X": -5, "Z": -3, "Type": "cwc_minecraft_red_rn"}, {"Y": 2, "X": -4, "Z": -3, "Type": "cwc_minecraft_red_rn"}, {"Y": 2, "X": -3, "Z": -3, "Type": "cwc_minecraft_red_rn"}], "XPos": -1.6999999880790726, "TimeAlive": 4417, "ZPos": -3.378165928257395, "Timestamp": "2018-03-30 17:58:40", "Yaw": 82.950035, "YPos": 2.8086870427730335, "BuilderGridRelative": [{"Y": -1, "X": -3, "Z": -1, "Type": "cwc_minecraft_orange_rn"}, {"Y": -1, "X": -1, "Z": -1, "Type": "cwc_minecraft_orange_rn"}, {"Y": -1, "X": -3, "Z": 1, "Type": "cwc_minecraft_orange_rn"}, {"Y": -1, "X": -1, "Z": 1, "Type": "cwc_minecraft_orange_rn"}, {"Y": 0, "X": -3, "Z": -1, "Type": "cwc_minecraft_red_rn"}, {"Y": 0, "X": -2, "Z": -1, "Type": "cwc_minecraft_red_rn"}, {"Y": 0, "X": -1, "Z": -1, "Type": "cwc_minecraft_red_rn"}, {"Y": 0, "X": -3, "Z": 0, "Type": "cwc_minecraft_red_rn"}, {"Y": 0, "X": -1, "Z": 0, "Type": "cwc_minecraft_red_rn"}, {"Y": 0, "X": -3, "Z": 1, "Type": "cwc_minecraft_red_rn"}, {"Y": 0, "X": -2, "Z": 1, "Type": "cwc_minecraft_red_rn"}, {"Y": 0, "X": -1, "Z": 1, "Type": "cwc_minecraft_red_rn"}], "DistanceTravelled": 2440, "BuilderInventory": [{"Index": 0, "Type": "cwc_minecraft_red_rn", "Quantity": 12}, {"Index": 1, "Type": "cwc_minecraft_orange_rn", "Quantity": 16}, {"Index": 2, "Type": "cwc_minecraft_yellow_rn", "Quantity": 20}, {"Index": 3, "Type": "cwc_minecraft_green_rn", "Quantity": 20}, {"Index": 4, "Type": "cwc_minecraft_blue_rn", "Quantity": 20}, {"Index": 5, "Type": "cwc_minecraft_purple_rn", "Quantity": 20}], "Pitch": 31.499958}, {"Timestamp": "2018-03-30 17:58:41", "ScreenshotPath": "213615-Builder-putdown.png"}, {"Timestamp": "2018-03-30 17:59:01", "Chat": ["<Architect> good job builder, we have completed yet another flawless structure!"], "ScreenshotPath": "233262-Builder-chat.png"}, {"BuilderGridAbsolute": [{"Y": 1, "X": -5, "Z": -5, "Type": "cwc_minecraft_orange_rn"}, {"Y": 1, "X": -3, "Z": -5, "Type": "cwc_minecraft_orange_rn"}, {"Y": 1, "X": -5, "Z": -3, "Type": "cwc_minecraft_orange_rn"}, {"Y": 1, "X": -3, "Z": -3, "Type": "cwc_minecraft_orange_rn"}, {"Y": 2, "X": -5, "Z": -5, "Type": "cwc_minecraft_red_rn"}, {"Y": 2, "X": -4, "Z": -5, "Type": "cwc_minecraft_red_rn"}, {"Y": 2, "X": -3, "Z": -5, "Type": "cwc_minecraft_red_rn"}, {"Y": 2, "X": -5, "Z": -4, "Type": "cwc_minecraft_red_rn"}, {"Y": 2, "X": -3, "Z": -4, "Type": "cwc_minecraft_red_rn"}, {"Y": 2, "X": -5, "Z": -3, "Type": "cwc_minecraft_red_rn"}, {"Y": 2, "X": -4, "Z": -3, "Type": "cwc_minecraft_red_rn"}, {"Y": 2, "X": -3, "Z": -3, "Type": "cwc_minecraft_red_rn"}], "XPos": -2.143432269722757, "TimeAlive": 4811, "ZPos": -2.4385868340380594, "Timestamp": "2018-03-30 17:59:01", "Yaw": 143.40007, "YPos": 3.0, "BuilderGridRelative": [{"Y": -2, "X": -2, "Z": -2, "Type": "cwc_minecraft_orange_rn"}, {"Y": -2, "X": 0, "Z": -2, "Type": "cwc_minecraft_orange_rn"}, {"Y": -2, "X": -2, "Z": 0, "Type": "cwc_minecraft_orange_rn"}, {"Y": -2, "X": 0, "Z": 0, "Type": "cwc_minecraft_orange_rn"}, {"Y": -1, "X": -2, "Z": -2, "Type": "cwc_minecraft_red_rn"}, {"Y": -1, "X": -1, "Z": -2, "Type": "cwc_minecraft_red_rn"}, {"Y": -1, "X": 0, "Z": -2, "Type": "cwc_minecraft_red_rn"}, {"Y": -1, "X": -2, "Z": -1, "Type": "cwc_minecraft_red_rn"}, {"Y": -1, "X": 0, "Z": -1, "Type": "cwc_minecraft_red_rn"}, {"Y": -1, "X": -2, "Z": 0, "Type": "cwc_minecraft_red_rn"}, {"Y": -1, "X": -1, "Z": 0, "Type": "cwc_minecraft_red_rn"}, {"Y": -1, "X": 0, "Z": 0, "Type": "cwc_minecraft_red_rn"}], "DistanceTravelled": 2825, "BuilderInventory": [{"Index": 0, "Type": "cwc_minecraft_red_rn", "Quantity": 12}, {"Index": 1, "Type": "cwc_minecraft_orange_rn", "Quantity": 16}, {"Index": 2, "Type": "cwc_minecraft_yellow_rn", "Quantity": 20}, {"Index": 3, "Type": "cwc_minecraft_green_rn", "Quantity": 20}, {"Index": 4, "Type": "cwc_minecraft_blue_rn", "Quantity": 20}, {"Index": 5, "Type": "cwc_minecraft_purple_rn", "Quantity": 20}], "Pitch": 43.049984}, {"Timestamp": "2018-03-30 17:59:11", "Chat": ["<Builder> its a table?"], "ScreenshotPath": "243208-Builder-chat.png"}, {"BuilderGridAbsolute": [{"Y": 1, "X": -5, "Z": -5, "Type": "cwc_minecraft_orange_rn"}, {"Y": 1, "X": -3, "Z": -5, "Type": "cwc_minecraft_orange_rn"}, {"Y": 1, "X": -5, "Z": -3, "Type": "cwc_minecraft_orange_rn"}, {"Y": 1, "X": -3, "Z": -3, "Type": "cwc_minecraft_orange_rn"}, {"Y": 2, "X": -5, "Z": -5, "Type": "cwc_minecraft_red_rn"}, {"Y": 2, "X": -4, "Z": -5, "Type": "cwc_minecraft_red_rn"}, {"Y": 2, "X": -3, "Z": -5, "Type": "cwc_minecraft_red_rn"}, {"Y": 2, "X": -5, "Z": -4, "Type": "cwc_minecraft_red_rn"}, {"Y": 2, "X": -3, "Z": -4, "Type": "cwc_minecraft_red_rn"}, {"Y": 2, "X": -5, "Z": -3, "Type": "cwc_minecraft_red_rn"}, {"Y": 2, "X": -4, "Z": -3, "Type": "cwc_minecraft_red_rn"}, {"Y": 2, "X": -3, "Z": -3, "Type": "cwc_minecraft_red_rn"}], "XPos": -2.143432269722757, "TimeAlive": 5010, "ZPos": -2.4385868340380594, "Timestamp": "2018-03-30 17:59:11", "Yaw": 143.40007, "YPos": 3.0, "BuilderGridRelative": [{"Y": -2, "X": -2, "Z": -2, "Type": "cwc_minecraft_orange_rn"}, {"Y": -2, "X": 0, "Z": -2, "Type": "cwc_minecraft_orange_rn"}, {"Y": -2, "X": -2, "Z": 0, "Type": "cwc_minecraft_orange_rn"}, {"Y": -2, "X": 0, "Z": 0, "Type": "cwc_minecraft_orange_rn"}, {"Y": -1, "X": -2, "Z": -2, "Type": "cwc_minecraft_red_rn"}, {"Y": -1, "X": -1, "Z": -2, "Type": "cwc_minecraft_red_rn"}, {"Y": -1, "X": 0, "Z": -2, "Type": "cwc_minecraft_red_rn"}, {"Y": -1, "X": -2, "Z": -1, "Type": "cwc_minecraft_red_rn"}, {"Y": -1, "X": 0, "Z": -1, "Type": "cwc_minecraft_red_rn"}, {"Y": -1, "X": -2, "Z": 0, "Type": "cwc_minecraft_red_rn"}, {"Y": -1, "X": -1, "Z": 0, "Type": "cwc_minecraft_red_rn"}, {"Y": -1, "X": 0, "Z": 0, "Type": "cwc_minecraft_red_rn"}], "DistanceTravelled": 2825, "BuilderInventory": [{"Index": 0, "Type": "cwc_minecraft_red_rn", "Quantity": 12}, {"Index": 1, "Type": "cwc_minecraft_orange_rn", "Quantity": 16}, {"Index": 2, "Type": "cwc_minecraft_yellow_rn", "Quantity": 20}, {"Index": 3, "Type": "cwc_minecraft_green_rn", "Quantity": 20}, {"Index": 4, "Type": "cwc_minecraft_blue_rn", "Quantity": 20}, {"Index": 5, "Type": "cwc_minecraft_purple_rn", "Quantity": 20}], "Pitch": 43.049984}, {"Timestamp": "2018-03-30 17:59:14", "Chat": ["<Builder> good job"], "ScreenshotPath": "246108-Builder-chat.png"}, {"BuilderGridAbsolute": [{"Y": 1, "X": -5, "Z": -5, "Type": "cwc_minecraft_orange_rn"}, {"Y": 1, "X": -3, "Z": -5, "Type": "cwc_minecraft_orange_rn"}, {"Y": 1, "X": -5, "Z": -3, "Type": "cwc_minecraft_orange_rn"}, {"Y": 1, "X": -3, "Z": -3, "Type": "cwc_minecraft_orange_rn"}, {"Y": 2, "X": -5, "Z": -5, "Type": "cwc_minecraft_red_rn"}, {"Y": 2, "X": -4, "Z": -5, "Type": "cwc_minecraft_red_rn"}, {"Y": 2, "X": -3, "Z": -5, "Type": "cwc_minecraft_red_rn"}, {"Y": 2, "X": -5, "Z": -4, "Type": "cwc_minecraft_red_rn"}, {"Y": 2, "X": -3, "Z": -4, "Type": "cwc_minecraft_red_rn"}, {"Y": 2, "X": -5, "Z": -3, "Type": "cwc_minecraft_red_rn"}, {"Y": 2, "X": -4, "Z": -3, "Type": "cwc_minecraft_red_rn"}, {"Y": 2, "X": -3, "Z": -3, "Type": "cwc_minecraft_red_rn"}], "XPos": -2.143432269722757, "TimeAlive": 5068, "ZPos": -2.4385868340380594, "Timestamp": "2018-03-30 17:59:14", "Yaw": 143.40007, "YPos": 3.0, "BuilderGridRelative": [{"Y": -2, "X": -2, "Z": -2, "Type": "cwc_minecraft_orange_rn"}, {"Y": -2, "X": 0, "Z": -2, "Type": "cwc_minecraft_orange_rn"}, {"Y": -2, "X": -2, "Z": 0, "Type": "cwc_minecraft_orange_rn"}, {"Y": -2, "X": 0, "Z": 0, "Type": "cwc_minecraft_orange_rn"}, {"Y": -1, "X": -2, "Z": -2, "Type": "cwc_minecraft_red_rn"}, {"Y": -1, "X": -1, "Z": -2, "Type": "cwc_minecraft_red_rn"}, {"Y": -1, "X": 0, "Z": -2, "Type": "cwc_minecraft_red_rn"}, {"Y": -1, "X": -2, "Z": -1, "Type": "cwc_minecraft_red_rn"}, {"Y": -1, "X": 0, "Z": -1, "Type": "cwc_minecraft_red_rn"}, {"Y": -1, "X": -2, "Z": 0, "Type": "cwc_minecraft_red_rn"}, {"Y": -1, "X": -1, "Z": 0, "Type": "cwc_minecraft_red_rn"}, {"Y": -1, "X": 0, "Z": 0, "Type": "cwc_minecraft_red_rn"}], "DistanceTravelled": 2825, "BuilderInventory": [{"Index": 0, "Type": "cwc_minecraft_red_rn", "Quantity": 12}, {"Index": 1, "Type": "cwc_minecraft_orange_rn", "Quantity": 16}, {"Index": 2, "Type": "cwc_minecraft_yellow_rn", "Quantity": 20}, {"Index": 3, "Type": "cwc_minecraft_green_rn", "Quantity": 20}, {"Index": 4, "Type": "cwc_minecraft_blue_rn", "Quantity": 20}, {"Index": 5, "Type": "cwc_minecraft_purple_rn", "Quantity": 20}], "Pitch": 43.049984}, {"Timestamp": "2018-03-30 17:59:18", "Chat": ["<Architect> i don't know what it is"], "ScreenshotPath": "250907-Builder-chat.png"}, {"BuilderGridAbsolute": [{"Y": 1, "X": -5, "Z": -5, "Type": "cwc_minecraft_orange_rn"}, {"Y": 1, "X": -3, "Z": -5, "Type": "cwc_minecraft_orange_rn"}, {"Y": 1, "X": -5, "Z": -3, "Type": "cwc_minecraft_orange_rn"}, {"Y": 1, "X": -3, "Z": -3, "Type": "cwc_minecraft_orange_rn"}, {"Y": 2, "X": -5, "Z": -5, "Type": "cwc_minecraft_red_rn"}, {"Y": 2, "X": -4, "Z": -5, "Type": "cwc_minecraft_red_rn"}, {"Y": 2, "X": -3, "Z": -5, "Type": "cwc_minecraft_red_rn"}, {"Y": 2, "X": -5, "Z": -4, "Type": "cwc_minecraft_red_rn"}, {"Y": 2, "X": -3, "Z": -4, "Type": "cwc_minecraft_red_rn"}, {"Y": 2, "X": -5, "Z": -3, "Type": "cwc_minecraft_red_rn"}, {"Y": 2, "X": -4, "Z": -3, "Type": "cwc_minecraft_red_rn"}, {"Y": 2, "X": -3, "Z": -3, "Type": "cwc_minecraft_red_rn"}], "XPos": -2.143432269722757, "TimeAlive": 5164, "ZPos": -2.4385868340380594, "Timestamp": "2018-03-30 17:59:18", "Yaw": 146.70003, "YPos": 3.0, "BuilderGridRelative": [{"Y": -2, "X": -2, "Z": -2, "Type": "cwc_minecraft_orange_rn"}, {"Y": -2, "X": 0, "Z": -2, "Type": "cwc_minecraft_orange_rn"}, {"Y": -2, "X": -2, "Z": 0, "Type": "cwc_minecraft_orange_rn"}, {"Y": -2, "X": 0, "Z": 0, "Type": "cwc_minecraft_orange_rn"}, {"Y": -1, "X": -2, "Z": -2, "Type": "cwc_minecraft_red_rn"}, {"Y": -1, "X": -1, "Z": -2, "Type": "cwc_minecraft_red_rn"}, {"Y": -1, "X": 0, "Z": -2, "Type": "cwc_minecraft_red_rn"}, {"Y": -1, "X": -2, "Z": -1, "Type": "cwc_minecraft_red_rn"}, {"Y": -1, "X": 0, "Z": -1, "Type": "cwc_minecraft_red_rn"}, {"Y": -1, "X": -2, "Z": 0, "Type": "cwc_minecraft_red_rn"}, {"Y": -1, "X": -1, "Z": 0, "Type": "cwc_minecraft_red_rn"}, {"Y": -1, "X": 0, "Z": 0, "Type": "cwc_minecraft_red_rn"}], "DistanceTravelled": 2825, "BuilderInventory": [{"Index": 0, "Type": "cwc_minecraft_red_rn", "Quantity": 12}, {"Index": 1, "Type": "cwc_minecraft_orange_rn", "Quantity": 16}, {"Index": 2, "Type": "cwc_minecraft_yellow_rn", "Quantity": 20}, {"Index": 3, "Type": "cwc_minecraft_green_rn", "Quantity": 20}, {"Index": 4, "Type": "cwc_minecraft_blue_rn", "Quantity": 20}, {"Index": 5, "Type": "cwc_minecraft_purple_rn", "Quantity": 20}], "Pitch": 43.049984}], "NumFixedViewers": 4, "TimeElapsed": 267.61118507385254}