{"WorldStates": [{"Timestamp": "2018-04-09 20:23:59", "Chat": ["<Builder> Mission has started."], "ScreenshotPath": "0-Builder-chat.png"}, {"BuilderGridAbsolute": [], "XPos": 0.0, "TimeAlive": 115, "ZPos": 0.0, "Timestamp": "2018-04-09 20:23:59", "Yaw": 0.0, "YPos": 1.0, "BuilderGridRelative": [], "DistanceTravelled": 0, "BuilderInventory": [{"Index": 0, "Type": "cwc_minecraft_red_rn", "Quantity": 20}, {"Index": 1, "Type": "cwc_minecraft_orange_rn", "Quantity": 20}, {"Index": 2, "Type": "cwc_minecraft_yellow_rn", "Quantity": 20}, {"Index": 3, "Type": "cwc_minecraft_green_rn", "Quantity": 20}, {"Index": 4, "Type": "cwc_minecraft_blue_rn", "Quantity": 20}, {"Index": 5, "Type": "cwc_minecraft_purple_rn", "Quantity": 20}], "Pitch": 0.0}, {"Timestamp": "2018-04-09 20:25:06", "Chat": ["<Architect> put 1 yellow block down towards the middle"], "ScreenshotPath": "66775-Builder-chat.png"}, {"BuilderGridAbsolute": [], "XPos": -2.37850085912645, "TimeAlive": 1450, "ZPos": -2.347660498516204, "Timestamp": "2018-04-09 20:25:06", "Yaw": -78.00001, "YPos": 1.0, "BuilderGridRelative": [], "DistanceTravelled": 343, "BuilderInventory": [{"Index": 0, "Type": "cwc_minecraft_red_rn", "Quantity": 20}, {"Index": 1, "Type": "cwc_minecraft_orange_rn", "Quantity": 20}, {"Index": 2, "Type": "cwc_minecraft_yellow_rn", "Quantity": 20}, {"Index": 3, "Type": "cwc_minecraft_green_rn", "Quantity": 20}, {"Index": 4, "Type": "cwc_minecraft_blue_rn", "Quantity": 20}, {"Index": 5, "Type": "cwc_minecraft_purple_rn", "Quantity": 20}], "Pitch": 27.59999}, {"BuilderGridAbsolute": [{"Y": 1, "X": 0, "Z": 0, "Type": "cwc_minecraft_yellow_rn"}], "XPos": -2.8926313991914943, "TimeAlive": 1601, "ZPos": 0.1773154600842778, "Timestamp": "2018-04-09 20:25:13", "Yaw": -87.90003, "YPos": 1.0, "ScreenshotPath": "74387-Builder-putdown.png", "BuilderGridRelative": [{"Y": 0, "X": 3, "Z": 0, "Type": "cwc_minecraft_yellow_rn"}], "DistanceTravelled": 601, "BuilderInventory": [{"Index": 0, "Type": "cwc_minecraft_red_rn", "Quantity": 20}, {"Index": 1, "Type": "cwc_minecraft_orange_rn", "Quantity": 20}, {"Index": 2, "Type": "cwc_minecraft_yellow_rn", "Quantity": 19}, {"Index": 3, "Type": "cwc_minecraft_green_rn", "Quantity": 20}, {"Index": 4, "Type": "cwc_minecraft_blue_rn", "Quantity": 20}, {"Index": 5, "Type": "cwc_minecraft_purple_rn", "Quantity": 20}], "Pitch": 27.14999}, {"Timestamp": "2018-04-09 20:25:16", "Chat": ["<Builder> ok"], "ScreenshotPath": "77487-Builder-chat.png"}, {"BuilderGridAbsolute": [{"Y": 1, "X": 0, "Z": 0, "Type": "cwc_minecraft_yellow_rn"}], "XPos": -2.8926313991914943, "TimeAlive": 1664, "ZPos": 0.1803758512721364, "Timestamp": "2018-04-09 20:25:16", "Yaw": -85.200035, "YPos": 1.0, "BuilderGridRelative": [{"Y": 0, "X": 3, "Z": 0, "Type": "cwc_minecraft_yellow_rn"}], "DistanceTravelled": 601, "BuilderInventory": [{"Index": 0, "Type": "cwc_minecraft_red_rn", "Quantity": 20}, {"Index": 1, "Type": "cwc_minecraft_orange_rn", "Quantity": 20}, {"Index": 2, "Type": "cwc_minecraft_yellow_rn", "Quantity": 19}, {"Index": 3, "Type": "cwc_minecraft_green_rn", "Quantity": 20}, {"Index": 4, "Type": "cwc_minecraft_blue_rn", "Quantity": 20}, {"Index": 5, "Type": "cwc_minecraft_purple_rn", "Quantity": 20}], "Pitch": 26.99999}, {"Timestamp": "2018-04-09 20:25:33", "Chat": ["<Architect> skip 1 square and put another yellow block"], "ScreenshotPath": "94033-Builder-chat.png"}, {"BuilderGridAbsolute": [{"Y": 1, "X": 0, "Z": 0, "Type": "cwc_minecraft_yellow_rn"}], "XPos": -2.8926313991914943, "TimeAlive": 1995, "ZPos": 0.1803758512721364, "Timestamp": "2018-04-09 20:25:33", "Yaw": -85.200035, "YPos": 1.0, "BuilderGridRelative": [{"Y": 0, "X": 3, "Z": 0, "Type": "cwc_minecraft_yellow_rn"}], "DistanceTravelled": 601, "BuilderInventory": [{"Index": 0, "Type": "cwc_minecraft_red_rn", "Quantity": 20}, {"Index": 1, "Type": "cwc_minecraft_orange_rn", "Quantity": 20}, {"Index": 2, "Type": "cwc_minecraft_yellow_rn", "Quantity": 19}, {"Index": 3, "Type": "cwc_minecraft_green_rn", "Quantity": 20}, {"Index": 4, "Type": "cwc_minecraft_blue_rn", "Quantity": 20}, {"Index": 5, "Type": "cwc_minecraft_purple_rn", "Quantity": 20}], "Pitch": 26.99999}, {"BuilderGridAbsolute": [{"Y": 1, "X": 0, "Z": 0, "Type": "cwc_minecraft_yellow_rn"}, {"Y": 1, "X": 0, "Z": 2, "Type": "cwc_minecraft_yellow_rn"}], "XPos": -3.1788213841758677, "TimeAlive": 2210, "ZPos": 1.656397046488209, "Timestamp": "2018-04-09 20:25:44", "Yaw": -82.35003, "YPos": 1.0, "ScreenshotPath": "104833-Builder-putdown.png", "BuilderGridRelative": [{"Y": 0, "X": 4, "Z": -1, "Type": "cwc_minecraft_yellow_rn"}, {"Y": 0, "X": 4, "Z": 1, "Type": "cwc_minecraft_yellow_rn"}], "DistanceTravelled": 751, "BuilderInventory": [{"Index": 0, "Type": "cwc_minecraft_red_rn", "Quantity": 20}, {"Index": 1, "Type": "cwc_minecraft_orange_rn", "Quantity": 20}, {"Index": 2, "Type": "cwc_minecraft_yellow_rn", "Quantity": 18}, {"Index": 3, "Type": "cwc_minecraft_green_rn", "Quantity": 20}, {"Index": 4, "Type": "cwc_minecraft_blue_rn", "Quantity": 20}, {"Index": 5, "Type": "cwc_minecraft_purple_rn", "Quantity": 20}], "Pitch": 23.249992}, {"Timestamp": "2018-04-09 20:25:59", "Chat": ["<Builder> ok"], "ScreenshotPath": "119630-Builder-chat.png"}, {"BuilderGridAbsolute": [{"Y": 1, "X": 0, "Z": 0, "Type": "cwc_minecraft_yellow_rn"}, {"Y": 1, "X": 0, "Z": 2, "Type": "cwc_minecraft_yellow_rn"}], "XPos": -3.1788213841758677, "TimeAlive": 2507, "ZPos": 1.6594106918458467, "Timestamp": "2018-04-09 20:25:59", "Yaw": -82.35003, "YPos": 1.0, "BuilderGridRelative": [{"Y": 0, "X": 4, "Z": -1, "Type": "cwc_minecraft_yellow_rn"}, {"Y": 0, "X": 4, "Z": 1, "Type": "cwc_minecraft_yellow_rn"}], "DistanceTravelled": 751, "BuilderInventory": [{"Index": 0, "Type": "cwc_minecraft_red_rn", "Quantity": 20}, {"Index": 1, "Type": "cwc_minecraft_orange_rn", "Quantity": 20}, {"Index": 2, "Type": "cwc_minecraft_yellow_rn", "Quantity": 18}, {"Index": 3, "Type": "cwc_minecraft_green_rn", "Quantity": 20}, {"Index": 4, "Type": "cwc_minecraft_blue_rn", "Quantity": 20}, {"Index": 5, "Type": "cwc_minecraft_purple_rn", "Quantity": 20}], "Pitch": 23.249992}, {"Timestamp": "2018-04-09 20:26:18", "Chat": ["<Architect> put 2 more to make a square"], "ScreenshotPath": "139379-Builder-chat.png"}, {"BuilderGridAbsolute": [{"Y": 1, "X": 0, "Z": 0, "Type": "cwc_minecraft_yellow_rn"}, {"Y": 1, "X": 0, "Z": 2, "Type": "cwc_minecraft_yellow_rn"}], "XPos": -3.1788213841758677, "TimeAlive": 2902, "ZPos": 1.6594106918458467, "Timestamp": "2018-04-09 20:26:18", "Yaw": -90.300095, "YPos": 1.0, "BuilderGridRelative": [{"Y": 0, "X": 4, "Z": -1, "Type": "cwc_minecraft_yellow_rn"}, {"Y": 0, "X": 4, "Z": 1, "Type": "cwc_minecraft_yellow_rn"}], "DistanceTravelled": 751, "BuilderInventory": [{"Index": 0, "Type": "cwc_minecraft_red_rn", "Quantity": 20}, {"Index": 1, "Type": "cwc_minecraft_orange_rn", "Quantity": 20}, {"Index": 2, "Type": "cwc_minecraft_yellow_rn", "Quantity": 18}, {"Index": 3, "Type": "cwc_minecraft_green_rn", "Quantity": 20}, {"Index": 4, "Type": "cwc_minecraft_blue_rn", "Quantity": 20}, {"Index": 5, "Type": "cwc_minecraft_purple_rn", "Quantity": 20}], "Pitch": 21.899996}, {"BuilderGridAbsolute": [{"Y": 1, "X": 0, "Z": 0, "Type": "cwc_minecraft_yellow_rn"}, {"Y": 1, "X": 0, "Z": 2, "Type": "cwc_minecraft_yellow_rn"}, {"Y": 1, "X": 2, "Z": 2, "Type": "cwc_minecraft_yellow_rn"}], "XPos": 1.8837729931041225, "TimeAlive": 3040, "ZPos": 4.9993978840426045, "Timestamp": "2018-04-09 20:26:25", "Yaw": -167.10011, "YPos": 1.0, "ScreenshotPath": "146327-Builder-putdown.png", "BuilderGridRelative": [{"Y": 0, "X": -1, "Z": -4, "Type": "cwc_minecraft_yellow_rn"}, {"Y": 0, "X": -1, "Z": -2, "Type": "cwc_minecraft_yellow_rn"}, {"Y": 0, "X": 1, "Z": -2, "Type": "cwc_minecraft_yellow_rn"}], "DistanceTravelled": 1795, "BuilderInventory": [{"Index": 0, "Type": "cwc_minecraft_red_rn", "Quantity": 20}, {"Index": 1, "Type": "cwc_minecraft_orange_rn", "Quantity": 20}, {"Index": 2, "Type": "cwc_minecraft_yellow_rn", "Quantity": 17}, {"Index": 3, "Type": "cwc_minecraft_green_rn", "Quantity": 20}, {"Index": 4, "Type": "cwc_minecraft_blue_rn", "Quantity": 20}, {"Index": 5, "Type": "cwc_minecraft_purple_rn", "Quantity": 20}], "Pitch": 33.74998}, {"BuilderGridAbsolute": [{"Y": 1, "X": 0, "Z": 0, "Type": "cwc_minecraft_yellow_rn"}, {"Y": 1, "X": 2, "Z": 0, "Type": "cwc_minecraft_yellow_rn"}, {"Y": 1, "X": 0, "Z": 2, "Type": "cwc_minecraft_yellow_rn"}, {"Y": 1, "X": 2, "Z": 2, "Type": "cwc_minecraft_yellow_rn"}], "XPos": 4.135541621833198, "TimeAlive": 3078, "ZPos": 4.108263006951814, "Timestamp": "2018-04-09 20:26:27", "Yaw": -201.75018, "YPos": 1.0, "ScreenshotPath": "148229-Builder-putdown.png", "BuilderGridRelative": [{"Y": 0, "X": -4, "Z": -4, "Type": "cwc_minecraft_yellow_rn"}, {"Y": 0, "X": -2, "Z": -4, "Type": "cwc_minecraft_yellow_rn"}, {"Y": 0, "X": -4, "Z": -2, "Type": "cwc_minecraft_yellow_rn"}, {"Y": 0, "X": -2, "Z": -2, "Type": "cwc_minecraft_yellow_rn"}], "DistanceTravelled": 2209, "BuilderInventory": [{"Index": 0, "Type": "cwc_minecraft_red_rn", "Quantity": 20}, {"Index": 1, "Type": "cwc_minecraft_orange_rn", "Quantity": 20}, {"Index": 2, "Type": "cwc_minecraft_yellow_rn", "Quantity": 16}, {"Index": 3, "Type": "cwc_minecraft_green_rn", "Quantity": 20}, {"Index": 4, "Type": "cwc_minecraft_blue_rn", "Quantity": 20}, {"Index": 5, "Type": "cwc_minecraft_purple_rn", "Quantity": 20}], "Pitch": 22.949978}, {"Timestamp": "2018-04-09 20:27:28", "Chat": ["<Architect> put one layer 9 orange blocks on top of the yellow layer"], "ScreenshotPath": "208733-Builder-chat.png"}, {"BuilderGridAbsolute": [{"Y": 1, "X": 0, "Z": 0, "Type": "cwc_minecraft_yellow_rn"}, {"Y": 1, "X": 2, "Z": 0, "Type": "cwc_minecraft_yellow_rn"}, {"Y": 1, "X": 0, "Z": 2, "Type": "cwc_minecraft_yellow_rn"}, {"Y": 1, "X": 2, "Z": 2, "Type": "cwc_minecraft_yellow_rn"}], "XPos": -2.0422895612665344, "TimeAlive": 4289, "ZPos": 1.7167851559334257, "Timestamp": "2018-04-09 20:27:28", "Yaw": -91.05022, "YPos": 1.0, "BuilderGridRelative": [{"Y": 0, "X": 3, "Z": -1, "Type": "cwc_minecraft_yellow_rn"}, {"Y": 0, "X": 5, "Z": -1, "Type": "cwc_minecraft_yellow_rn"}, {"Y": 0, "X": 3, "Z": 1, "Type": "cwc_minecraft_yellow_rn"}, {"Y": 0, "X": 5, "Z": 1, "Type": "cwc_minecraft_yellow_rn"}], "DistanceTravelled": 3003, "BuilderInventory": [{"Index": 0, "Type": "cwc_minecraft_red_rn", "Quantity": 20}, {"Index": 1, "Type": "cwc_minecraft_orange_rn", "Quantity": 20}, {"Index": 2, "Type": "cwc_minecraft_yellow_rn", "Quantity": 16}, {"Index": 3, "Type": "cwc_minecraft_green_rn", "Quantity": 20}, {"Index": 4, "Type": "cwc_minecraft_blue_rn", "Quantity": 20}, {"Index": 5, "Type": "cwc_minecraft_purple_rn", "Quantity": 20}], "Pitch": 31.349995}, {"BuilderGridAbsolute": [{"Y": 1, "X": 2, "Z": 0, "Type": "cwc_minecraft_yellow_rn"}, {"Y": 1, "X": 0, "Z": 2, "Type": "cwc_minecraft_yellow_rn"}, {"Y": 1, "X": 2, "Z": 2, "Type": "cwc_minecraft_yellow_rn"}], "XPos": -2.0422895612665344, "TimeAlive": 4441, "ZPos": 1.7167851559334257, "Timestamp": "2018-04-09 20:27:35", "Yaw": -111.45022, "YPos": 1.0, "BuilderGridRelative": [{"Y": 0, "X": 5, "Z": -1, "Type": "cwc_minecraft_yellow_rn"}, {"Y": 0, "X": 3, "Z": 1, "Type": "cwc_minecraft_yellow_rn"}, {"Y": 0, "X": 5, "Z": 1, "Type": "cwc_minecraft_yellow_rn"}], "DistanceTravelled": 3003, "BuilderInventory": [{"Index": 0, "Type": "cwc_minecraft_red_rn", "Quantity": 20}, {"Index": 1, "Type": "cwc_minecraft_orange_rn", "Quantity": 20}, {"Index": 2, "Type": "cwc_minecraft_yellow_rn", "Quantity": 17}, {"Index": 3, "Type": "cwc_minecraft_green_rn", "Quantity": 20}, {"Index": 4, "Type": "cwc_minecraft_blue_rn", "Quantity": 20}, {"Index": 5, "Type": "cwc_minecraft_purple_rn", "Quantity": 20}], "Pitch": 12.899993}, {"Timestamp": "2018-04-09 20:27:35", "ScreenshotPath": "216432-Builder-pickup.png"}, {"BuilderGridAbsolute": [{"Y": 1, "X": 0, "Z": 0, "Type": "cwc_minecraft_yellow_rn"}, {"Y": 1, "X": 2, "Z": 0, "Type": "cwc_minecraft_yellow_rn"}, {"Y": 1, "X": 0, "Z": 2, "Type": "cwc_minecraft_yellow_rn"}, {"Y": 1, "X": 2, "Z": 2, "Type": "cwc_minecraft_yellow_rn"}], "XPos": -2.0422895612665344, "TimeAlive": 4485, "ZPos": 1.7167851559334257, "Timestamp": "2018-04-09 20:27:38", "Yaw": -113.25022, "YPos": 1.0, "ScreenshotPath": "218583-Builder-putdown.png", "BuilderGridRelative": [{"Y": 0, "X": 3, "Z": -1, "Type": "cwc_minecraft_yellow_rn"}, {"Y": 0, "X": 5, "Z": -1, "Type": "cwc_minecraft_yellow_rn"}, {"Y": 0, "X": 3, "Z": 1, "Type": "cwc_minecraft_yellow_rn"}, {"Y": 0, "X": 5, "Z": 1, "Type": "cwc_minecraft_yellow_rn"}], "DistanceTravelled": 3003, "BuilderInventory": [{"Index": 0, "Type": "cwc_minecraft_red_rn", "Quantity": 20}, {"Index": 1, "Type": "cwc_minecraft_orange_rn", "Quantity": 20}, {"Index": 2, "Type": "cwc_minecraft_yellow_rn", "Quantity": 16}, {"Index": 3, "Type": "cwc_minecraft_green_rn", "Quantity": 20}, {"Index": 4, "Type": "cwc_minecraft_blue_rn", "Quantity": 20}, {"Index": 5, "Type": "cwc_minecraft_purple_rn", "Quantity": 20}], "Pitch": 29.54999}, {"BuilderGridAbsolute": [{"Y": 1, "X": 0, "Z": 0, "Type": "cwc_minecraft_yellow_rn"}, {"Y": 1, "X": 2, "Z": 0, "Type": "cwc_minecraft_yellow_rn"}, {"Y": 1, "X": 0, "Z": 2, "Type": "cwc_minecraft_yellow_rn"}, {"Y": 1, "X": 2, "Z": 2, "Type": "cwc_minecraft_yellow_rn"}, {"Y": 2, "X": 0, "Z": 0, "Type": "cwc_minecraft_orange_rn"}], "XPos": -2.0422895612665344, "TimeAlive": 4536, "ZPos": 1.7167851559334257, "Timestamp": "2018-04-09 20:27:40", "Yaw": -112.65025, "YPos": 1.0, "ScreenshotPath": "221131-Builder-putdown.png", "BuilderGridRelative": [{"Y": 0, "X": 3, "Z": -1, "Type": "cwc_minecraft_yellow_rn"}, {"Y": 0, "X": 5, "Z": -1, "Type": "cwc_minecraft_yellow_rn"}, {"Y": 0, "X": 3, "Z": 1, "Type": "cwc_minecraft_yellow_rn"}, {"Y": 0, "X": 5, "Z": 1, "Type": "cwc_minecraft_yellow_rn"}, {"Y": 1, "X": 3, "Z": -1, "Type": "cwc_minecraft_orange_rn"}], "DistanceTravelled": 3003, "BuilderInventory": [{"Index": 0, "Type": "cwc_minecraft_red_rn", "Quantity": 20}, {"Index": 1, "Type": "cwc_minecraft_orange_rn", "Quantity": 19}, {"Index": 2, "Type": "cwc_minecraft_yellow_rn", "Quantity": 16}, {"Index": 3, "Type": "cwc_minecraft_green_rn", "Quantity": 20}, {"Index": 4, "Type": "cwc_minecraft_blue_rn", "Quantity": 20}, {"Index": 5, "Type": "cwc_minecraft_purple_rn", "Quantity": 20}], "Pitch": 11.249991}, {"BuilderGridAbsolute": [{"Y": 1, "X": 0, "Z": 0, "Type": "cwc_minecraft_yellow_rn"}, {"Y": 1, "X": 2, "Z": 0, "Type": "cwc_minecraft_yellow_rn"}, {"Y": 1, "X": 0, "Z": 2, "Type": "cwc_minecraft_yellow_rn"}, {"Y": 1, "X": 2, "Z": 2, "Type": "cwc_minecraft_yellow_rn"}, {"Y": 2, "X": 0, "Z": 0, "Type": "cwc_minecraft_orange_rn"}, {"Y": 2, "X": 0, "Z": 1, "Type": "cwc_minecraft_orange_rn"}], "XPos": -2.0422895612665344, "TimeAlive": 4560, "ZPos": 1.7167851559334257, "Timestamp": "2018-04-09 20:27:41", "Yaw": -106.05025, "YPos": 1.0, "ScreenshotPath": "222331-Builder-putdown.png", "BuilderGridRelative": [{"Y": 0, "X": 3, "Z": -1, "Type": "cwc_minecraft_yellow_rn"}, {"Y": 0, "X": 5, "Z": -1, "Type": "cwc_minecraft_yellow_rn"}, {"Y": 0, "X": 3, "Z": 1, "Type": "cwc_minecraft_yellow_rn"}, {"Y": 0, "X": 5, "Z": 1, "Type": "cwc_minecraft_yellow_rn"}, {"Y": 1, "X": 3, "Z": -1, "Type": "cwc_minecraft_orange_rn"}, {"Y": 1, "X": 3, "Z": 0, "Type": "cwc_minecraft_orange_rn"}], "DistanceTravelled": 3003, "BuilderInventory": [{"Index": 0, "Type": "cwc_minecraft_red_rn", "Quantity": 20}, {"Index": 1, "Type": "cwc_minecraft_orange_rn", "Quantity": 18}, {"Index": 2, "Type": "cwc_minecraft_yellow_rn", "Quantity": 16}, {"Index": 3, "Type": "cwc_minecraft_green_rn", "Quantity": 20}, {"Index": 4, "Type": "cwc_minecraft_blue_rn", "Quantity": 20}, {"Index": 5, "Type": "cwc_minecraft_purple_rn", "Quantity": 20}], "Pitch": 6.5999904}, {"BuilderGridAbsolute": [{"Y": 1, "X": 0, "Z": 0, "Type": "cwc_minecraft_yellow_rn"}, {"Y": 1, "X": 2, "Z": 0, "Type": "cwc_minecraft_yellow_rn"}, {"Y": 1, "X": 0, "Z": 2, "Type": "cwc_minecraft_yellow_rn"}, {"Y": 1, "X": 2, "Z": 2, "Type": "cwc_minecraft_yellow_rn"}, {"Y": 2, "X": 0, "Z": 0, "Type": "cwc_minecraft_orange_rn"}, {"Y": 2, "X": 0, "Z": 1, "Type": "cwc_minecraft_orange_rn"}, {"Y": 2, "X": 0, "Z": 2, "Type": "cwc_minecraft_orange_rn"}], "XPos": -1.4348988506119138, "TimeAlive": 4589, "ZPos": 3.780187563059564, "Timestamp": "2018-04-09 20:27:43", "Yaw": -127.80024, "YPos": 1.0, "ScreenshotPath": "223781-Builder-putdown.png", "BuilderGridRelative": [{"Y": 0, "X": 2, "Z": -3, "Type": "cwc_minecraft_yellow_rn"}, {"Y": 0, "X": 4, "Z": -3, "Type": "cwc_minecraft_yellow_rn"}, {"Y": 0, "X": 2, "Z": -1, "Type": "cwc_minecraft_yellow_rn"}, {"Y": 0, "X": 4, "Z": -1, "Type": "cwc_minecraft_yellow_rn"}, {"Y": 1, "X": 2, "Z": -3, "Type": "cwc_minecraft_orange_rn"}, {"Y": 1, "X": 2, "Z": -2, "Type": "cwc_minecraft_orange_rn"}, {"Y": 1, "X": 2, "Z": -1, "Type": "cwc_minecraft_orange_rn"}], "DistanceTravelled": 3218, "BuilderInventory": [{"Index": 0, "Type": "cwc_minecraft_red_rn", "Quantity": 20}, {"Index": 1, "Type": "cwc_minecraft_orange_rn", "Quantity": 17}, {"Index": 2, "Type": "cwc_minecraft_yellow_rn", "Quantity": 16}, {"Index": 3, "Type": "cwc_minecraft_green_rn", "Quantity": 20}, {"Index": 4, "Type": "cwc_minecraft_blue_rn", "Quantity": 20}, {"Index": 5, "Type": "cwc_minecraft_purple_rn", "Quantity": 20}], "Pitch": 12.899988}, {"BuilderGridAbsolute": [{"Y": 1, "X": 0, "Z": 0, "Type": "cwc_minecraft_yellow_rn"}, {"Y": 1, "X": 2, "Z": 0, "Type": "cwc_minecraft_yellow_rn"}, {"Y": 1, "X": 0, "Z": 2, "Type": "cwc_minecraft_yellow_rn"}, {"Y": 1, "X": 2, "Z": 2, "Type": "cwc_minecraft_yellow_rn"}, {"Y": 2, "X": 0, "Z": 0, "Type": "cwc_minecraft_orange_rn"}, {"Y": 2, "X": 0, "Z": 1, "Type": "cwc_minecraft_orange_rn"}, {"Y": 2, "X": 1, "Z": 1, "Type": "cwc_minecraft_orange_rn"}, {"Y": 2, "X": 0, "Z": 2, "Type": "cwc_minecraft_orange_rn"}], "XPos": 3.463706181625479, "TimeAlive": 4654, "ZPos": 3.801341600600216, "Timestamp": "2018-04-09 20:27:46", "Yaw": -224.85022, "YPos": 1.0, "ScreenshotPath": "227031-Builder-putdown.png", "BuilderGridRelative": [{"Y": 0, "X": -3, "Z": -3, "Type": "cwc_minecraft_yellow_rn"}, {"Y": 0, "X": -1, "Z": -3, "Type": "cwc_minecraft_yellow_rn"}, {"Y": 0, "X": -3, "Z": -1, "Type": "cwc_minecraft_yellow_rn"}, {"Y": 0, "X": -1, "Z": -1, "Type": "cwc_minecraft_yellow_rn"}, {"Y": 1, "X": -3, "Z": -3, "Type": "cwc_minecraft_orange_rn"}, {"Y": 1, "X": -3, "Z": -2, "Type": "cwc_minecraft_orange_rn"}, {"Y": 1, "X": -2, "Z": -2, "Type": "cwc_minecraft_orange_rn"}, {"Y": 1, "X": -3, "Z": -1, "Type": "cwc_minecraft_orange_rn"}], "DistanceTravelled": 4074, "BuilderInventory": [{"Index": 0, "Type": "cwc_minecraft_red_rn", "Quantity": 20}, {"Index": 1, "Type": "cwc_minecraft_orange_rn", "Quantity": 16}, {"Index": 2, "Type": "cwc_minecraft_yellow_rn", "Quantity": 16}, {"Index": 3, "Type": "cwc_minecraft_green_rn", "Quantity": 20}, {"Index": 4, "Type": "cwc_minecraft_blue_rn", "Quantity": 20}, {"Index": 5, "Type": "cwc_minecraft_purple_rn", "Quantity": 20}], "Pitch": 4.349987}, {"BuilderGridAbsolute": [{"Y": 1, "X": 0, "Z": 0, "Type": "cwc_minecraft_yellow_rn"}, {"Y": 1, "X": 2, "Z": 0, "Type": "cwc_minecraft_yellow_rn"}, {"Y": 1, "X": 0, "Z": 2, "Type": "cwc_minecraft_yellow_rn"}, {"Y": 1, "X": 2, "Z": 2, "Type": "cwc_minecraft_yellow_rn"}, {"Y": 2, "X": 0, "Z": 0, "Type": "cwc_minecraft_orange_rn"}, {"Y": 2, "X": 0, "Z": 1, "Type": "cwc_minecraft_orange_rn"}, {"Y": 2, "X": 1, "Z": 1, "Type": "cwc_minecraft_orange_rn"}, {"Y": 2, "X": 0, "Z": 2, "Type": "cwc_minecraft_orange_rn"}, {"Y": 2, "X": 1, "Z": 2, "Type": "cwc_minecraft_orange_rn"}], "XPos": 3.463706181625479, "TimeAlive": 4675, "ZPos": 3.801341600600216, "Timestamp": "2018-04-09 20:27:47", "Yaw": -240.60023, "YPos": 1.0, "ScreenshotPath": "228080-Builder-putdown.png", "BuilderGridRelative": [{"Y": 0, "X": -3, "Z": -3, "Type": "cwc_minecraft_yellow_rn"}, {"Y": 0, "X": -1, "Z": -3, "Type": "cwc_minecraft_yellow_rn"}, {"Y": 0, "X": -3, "Z": -1, "Type": "cwc_minecraft_yellow_rn"}, {"Y": 0, "X": -1, "Z": -1, "Type": "cwc_minecraft_yellow_rn"}, {"Y": 1, "X": -3, "Z": -3, "Type": "cwc_minecraft_orange_rn"}, {"Y": 1, "X": -3, "Z": -2, "Type": "cwc_minecraft_orange_rn"}, {"Y": 1, "X": -2, "Z": -2, "Type": "cwc_minecraft_orange_rn"}, {"Y": 1, "X": -3, "Z": -1, "Type": "cwc_minecraft_orange_rn"}, {"Y": 1, "X": -2, "Z": -1, "Type": "cwc_minecraft_orange_rn"}], "DistanceTravelled": 4074, "BuilderInventory": [{"Index": 0, "Type": "cwc_minecraft_red_rn", "Quantity": 20}, {"Index": 1, "Type": "cwc_minecraft_orange_rn", "Quantity": 15}, {"Index": 2, "Type": "cwc_minecraft_yellow_rn", "Quantity": 16}, {"Index": 3, "Type": "cwc_minecraft_green_rn", "Quantity": 20}, {"Index": 4, "Type": "cwc_minecraft_blue_rn", "Quantity": 20}, {"Index": 5, "Type": "cwc_minecraft_purple_rn", "Quantity": 20}], "Pitch": 6.749987}, {"BuilderGridAbsolute": [{"Y": 1, "X": 0, "Z": 0, "Type": "cwc_minecraft_yellow_rn"}, {"Y": 1, "X": 2, "Z": 0, "Type": "cwc_minecraft_yellow_rn"}, {"Y": 1, "X": 0, "Z": 2, "Type": "cwc_minecraft_yellow_rn"}, {"Y": 1, "X": 2, "Z": 2, "Type": "cwc_minecraft_yellow_rn"}, {"Y": 2, "X": 0, "Z": 0, "Type": "cwc_minecraft_orange_rn"}, {"Y": 2, "X": 0, "Z": 1, "Type": "cwc_minecraft_orange_rn"}, {"Y": 2, "X": 1, "Z": 1, "Type": "cwc_minecraft_orange_rn"}, {"Y": 2, "X": 0, "Z": 2, "Type": "cwc_minecraft_orange_rn"}, {"Y": 2, "X": 1, "Z": 2, "Type": "cwc_minecraft_orange_rn"}, {"Y": 2, "X": 2, "Z": 2, "Type": "cwc_minecraft_orange_rn"}], "XPos": 3.463706181625479, "TimeAlive": 4694, "ZPos": 3.801341600600216, "Timestamp": "2018-04-09 20:27:48", "Yaw": -227.55028, "YPos": 1.0, "ScreenshotPath": "229031-Builder-putdown.png", "BuilderGridRelative": [{"Y": 0, "X": -3, "Z": -3, "Type": "cwc_minecraft_yellow_rn"}, {"Y": 0, "X": -1, "Z": -3, "Type": "cwc_minecraft_yellow_rn"}, {"Y": 0, "X": -3, "Z": -1, "Type": "cwc_minecraft_yellow_rn"}, {"Y": 0, "X": -1, "Z": -1, "Type": "cwc_minecraft_yellow_rn"}, {"Y": 1, "X": -3, "Z": -3, "Type": "cwc_minecraft_orange_rn"}, {"Y": 1, "X": -3, "Z": -2, "Type": "cwc_minecraft_orange_rn"}, {"Y": 1, "X": -2, "Z": -2, "Type": "cwc_minecraft_orange_rn"}, {"Y": 1, "X": -3, "Z": -1, "Type": "cwc_minecraft_orange_rn"}, {"Y": 1, "X": -2, "Z": -1, "Type": "cwc_minecraft_orange_rn"}, {"Y": 1, "X": -1, "Z": -1, "Type": "cwc_minecraft_orange_rn"}], "DistanceTravelled": 4074, "BuilderInventory": [{"Index": 0, "Type": "cwc_minecraft_red_rn", "Quantity": 20}, {"Index": 1, "Type": "cwc_minecraft_orange_rn", "Quantity": 14}, {"Index": 2, "Type": "cwc_minecraft_yellow_rn", "Quantity": 16}, {"Index": 3, "Type": "cwc_minecraft_green_rn", "Quantity": 20}, {"Index": 4, "Type": "cwc_minecraft_blue_rn", "Quantity": 20}, {"Index": 5, "Type": "cwc_minecraft_purple_rn", "Quantity": 20}], "Pitch": 12.599991}, {"BuilderGridAbsolute": [{"Y": 1, "X": 0, "Z": 0, "Type": "cwc_minecraft_yellow_rn"}, {"Y": 1, "X": 2, "Z": 0, "Type": "cwc_minecraft_yellow_rn"}, {"Y": 1, "X": 0, "Z": 2, "Type": "cwc_minecraft_yellow_rn"}, {"Y": 1, "X": 2, "Z": 2, "Type": "cwc_minecraft_yellow_rn"}, {"Y": 2, "X": 0, "Z": 0, "Type": "cwc_minecraft_orange_rn"}, {"Y": 2, "X": 0, "Z": 1, "Type": "cwc_minecraft_orange_rn"}, {"Y": 2, "X": 1, "Z": 1, "Type": "cwc_minecraft_orange_rn"}, {"Y": 2, "X": 2, "Z": 1, "Type": "cwc_minecraft_orange_rn"}, {"Y": 2, "X": 0, "Z": 2, "Type": "cwc_minecraft_orange_rn"}, {"Y": 2, "X": 1, "Z": 2, "Type": "cwc_minecraft_orange_rn"}, {"Y": 2, "X": 2, "Z": 2, "Type": "cwc_minecraft_orange_rn"}], "XPos": 5.075083634556717, "TimeAlive": 4735, "ZPos": 1.0647339573953714, "Timestamp": "2018-04-09 20:27:50", "Yaw": -283.35025, "YPos": 1.0, "ScreenshotPath": "231080-Builder-putdown.png", "BuilderGridRelative": [{"Y": 0, "X": -5, "Z": -1, "Type": "cwc_minecraft_yellow_rn"}, {"Y": 0, "X": -3, "Z": -1, "Type": "cwc_minecraft_yellow_rn"}, {"Y": 0, "X": -5, "Z": 1, "Type": "cwc_minecraft_yellow_rn"}, {"Y": 0, "X": -3, "Z": 1, "Type": "cwc_minecraft_yellow_rn"}, {"Y": 1, "X": -5, "Z": -1, "Type": "cwc_minecraft_orange_rn"}, {"Y": 1, "X": -5, "Z": 0, "Type": "cwc_minecraft_orange_rn"}, {"Y": 1, "X": -4, "Z": 0, "Type": "cwc_minecraft_orange_rn"}, {"Y": 1, "X": -3, "Z": 0, "Type": "cwc_minecraft_orange_rn"}, {"Y": 1, "X": -5, "Z": 1, "Type": "cwc_minecraft_orange_rn"}, {"Y": 1, "X": -4, "Z": 1, "Type": "cwc_minecraft_orange_rn"}, {"Y": 1, "X": -3, "Z": 1, "Type": "cwc_minecraft_orange_rn"}], "DistanceTravelled": 4395, "BuilderInventory": [{"Index": 0, "Type": "cwc_minecraft_red_rn", "Quantity": 20}, {"Index": 1, "Type": "cwc_minecraft_orange_rn", "Quantity": 13}, {"Index": 2, "Type": "cwc_minecraft_yellow_rn", "Quantity": 16}, {"Index": 3, "Type": "cwc_minecraft_green_rn", "Quantity": 20}, {"Index": 4, "Type": "cwc_minecraft_blue_rn", "Quantity": 20}, {"Index": 5, "Type": "cwc_minecraft_purple_rn", "Quantity": 20}], "Pitch": 3.5999932}, {"BuilderGridAbsolute": [{"Y": 1, "X": 0, "Z": 0, "Type": "cwc_minecraft_yellow_rn"}, {"Y": 1, "X": 2, "Z": 0, "Type": "cwc_minecraft_yellow_rn"}, {"Y": 1, "X": 0, "Z": 2, "Type": "cwc_minecraft_yellow_rn"}, {"Y": 1, "X": 2, "Z": 2, "Type": "cwc_minecraft_yellow_rn"}, {"Y": 2, "X": 0, "Z": 0, "Type": "cwc_minecraft_orange_rn"}, {"Y": 2, "X": 1, "Z": 0, "Type": "cwc_minecraft_orange_rn"}, {"Y": 2, "X": 0, "Z": 1, "Type": "cwc_minecraft_orange_rn"}, {"Y": 2, "X": 1, "Z": 1, "Type": "cwc_minecraft_orange_rn"}, {"Y": 2, "X": 2, "Z": 1, "Type": "cwc_minecraft_orange_rn"}, {"Y": 2, "X": 0, "Z": 2, "Type": "cwc_minecraft_orange_rn"}, {"Y": 2, "X": 1, "Z": 2, "Type": "cwc_minecraft_orange_rn"}, {"Y": 2, "X": 2, "Z": 2, "Type": "cwc_minecraft_orange_rn"}], "XPos": 4.596816840919655, "TimeAlive": 4769, "ZPos": -1.224399416179992, "Timestamp": "2018-04-09 20:27:52", "Yaw": -303.4503, "YPos": 1.0, "ScreenshotPath": "232781-Builder-putdown.png", "BuilderGridRelative": [{"Y": 0, "X": -4, "Z": 2, "Type": "cwc_minecraft_yellow_rn"}, {"Y": 0, "X": -2, "Z": 2, "Type": "cwc_minecraft_yellow_rn"}, {"Y": 0, "X": -4, "Z": 4, "Type": "cwc_minecraft_yellow_rn"}, {"Y": 0, "X": -2, "Z": 4, "Type": "cwc_minecraft_yellow_rn"}, {"Y": 1, "X": -4, "Z": 2, "Type": "cwc_minecraft_orange_rn"}, {"Y": 1, "X": -3, "Z": 2, "Type": "cwc_minecraft_orange_rn"}, {"Y": 1, "X": -4, "Z": 3, "Type": "cwc_minecraft_orange_rn"}, {"Y": 1, "X": -3, "Z": 3, "Type": "cwc_minecraft_orange_rn"}, {"Y": 1, "X": -2, "Z": 3, "Type": "cwc_minecraft_orange_rn"}, {"Y": 1, "X": -4, "Z": 4, "Type": "cwc_minecraft_orange_rn"}, {"Y": 1, "X": -3, "Z": 4, "Type": "cwc_minecraft_orange_rn"}, {"Y": 1, "X": -2, "Z": 4, "Type": "cwc_minecraft_orange_rn"}], "DistanceTravelled": 4628, "BuilderInventory": [{"Index": 0, "Type": "cwc_minecraft_red_rn", "Quantity": 20}, {"Index": 1, "Type": "cwc_minecraft_orange_rn", "Quantity": 12}, {"Index": 2, "Type": "cwc_minecraft_yellow_rn", "Quantity": 16}, {"Index": 3, "Type": "cwc_minecraft_green_rn", "Quantity": 20}, {"Index": 4, "Type": "cwc_minecraft_blue_rn", "Quantity": 20}, {"Index": 5, "Type": "cwc_minecraft_purple_rn", "Quantity": 20}], "Pitch": 3.5999925}, {"BuilderGridAbsolute": [{"Y": 1, "X": 0, "Z": 0, "Type": "cwc_minecraft_yellow_rn"}, {"Y": 1, "X": 2, "Z": 0, "Type": "cwc_minecraft_yellow_rn"}, {"Y": 1, "X": 0, "Z": 2, "Type": "cwc_minecraft_yellow_rn"}, {"Y": 1, "X": 2, "Z": 2, "Type": "cwc_minecraft_yellow_rn"}, {"Y": 2, "X": 0, "Z": 0, "Type": "cwc_minecraft_orange_rn"}, {"Y": 2, "X": 1, "Z": 0, "Type": "cwc_minecraft_orange_rn"}, {"Y": 2, "X": 2, "Z": 0, "Type": "cwc_minecraft_orange_rn"}, {"Y": 2, "X": 0, "Z": 1, "Type": "cwc_minecraft_orange_rn"}, {"Y": 2, "X": 1, "Z": 1, "Type": "cwc_minecraft_orange_rn"}, {"Y": 2, "X": 2, "Z": 1, "Type": "cwc_minecraft_orange_rn"}, {"Y": 2, "X": 0, "Z": 2, "Type": "cwc_minecraft_orange_rn"}, {"Y": 2, "X": 1, "Z": 2, "Type": "cwc_minecraft_orange_rn"}, {"Y": 2, "X": 2, "Z": 2, "Type": "cwc_minecraft_orange_rn"}], "XPos": 4.596816840919655, "TimeAlive": 4784, "ZPos": -1.224399416179992, "Timestamp": "2018-04-09 20:27:52", "Yaw": -316.65027, "YPos": 1.0, "ScreenshotPath": "233530-Builder-putdown.png", "BuilderGridRelative": [{"Y": 0, "X": -4, "Z": 2, "Type": "cwc_minecraft_yellow_rn"}, {"Y": 0, "X": -2, "Z": 2, "Type": "cwc_minecraft_yellow_rn"}, {"Y": 0, "X": -4, "Z": 4, "Type": "cwc_minecraft_yellow_rn"}, {"Y": 0, "X": -2, "Z": 4, "Type": "cwc_minecraft_yellow_rn"}, {"Y": 1, "X": -4, "Z": 2, "Type": "cwc_minecraft_orange_rn"}, {"Y": 1, "X": -3, "Z": 2, "Type": "cwc_minecraft_orange_rn"}, {"Y": 1, "X": -2, "Z": 2, "Type": "cwc_minecraft_orange_rn"}, {"Y": 1, "X": -4, "Z": 3, "Type": "cwc_minecraft_orange_rn"}, {"Y": 1, "X": -3, "Z": 3, "Type": "cwc_minecraft_orange_rn"}, {"Y": 1, "X": -2, "Z": 3, "Type": "cwc_minecraft_orange_rn"}, {"Y": 1, "X": -4, "Z": 4, "Type": "cwc_minecraft_orange_rn"}, {"Y": 1, "X": -3, "Z": 4, "Type": "cwc_minecraft_orange_rn"}, {"Y": 1, "X": -2, "Z": 4, "Type": "cwc_minecraft_orange_rn"}], "DistanceTravelled": 4628, "BuilderInventory": [{"Index": 0, "Type": "cwc_minecraft_red_rn", "Quantity": 20}, {"Index": 1, "Type": "cwc_minecraft_orange_rn", "Quantity": 11}, {"Index": 2, "Type": "cwc_minecraft_yellow_rn", "Quantity": 16}, {"Index": 3, "Type": "cwc_minecraft_green_rn", "Quantity": 20}, {"Index": 4, "Type": "cwc_minecraft_blue_rn", "Quantity": 20}, {"Index": 5, "Type": "cwc_minecraft_purple_rn", "Quantity": 20}], "Pitch": 3.5999925}, {"Timestamp": "2018-04-09 20:28:00", "Chat": ["<Builder> like that?"], "ScreenshotPath": "240480-Builder-chat.png"}, {"BuilderGridAbsolute": [{"Y": 1, "X": 0, "Z": 0, "Type": "cwc_minecraft_yellow_rn"}, {"Y": 1, "X": 2, "Z": 0, "Type": "cwc_minecraft_yellow_rn"}, {"Y": 1, "X": 0, "Z": 2, "Type": "cwc_minecraft_yellow_rn"}, {"Y": 1, "X": 2, "Z": 2, "Type": "cwc_minecraft_yellow_rn"}, {"Y": 2, "X": 0, "Z": 0, "Type": "cwc_minecraft_orange_rn"}, {"Y": 2, "X": 1, "Z": 0, "Type": "cwc_minecraft_orange_rn"}, {"Y": 2, "X": 2, "Z": 0, "Type": "cwc_minecraft_orange_rn"}, {"Y": 2, "X": 0, "Z": 1, "Type": "cwc_minecraft_orange_rn"}, {"Y": 2, "X": 1, "Z": 1, "Type": "cwc_minecraft_orange_rn"}, {"Y": 2, "X": 2, "Z": 1, "Type": "cwc_minecraft_orange_rn"}, {"Y": 2, "X": 0, "Z": 2, "Type": "cwc_minecraft_orange_rn"}, {"Y": 2, "X": 1, "Z": 2, "Type": "cwc_minecraft_orange_rn"}, {"Y": 2, "X": 2, "Z": 2, "Type": "cwc_minecraft_orange_rn"}], "XPos": 3.820968861964912, "TimeAlive": 4924, "ZPos": -0.4835701169625762, "Timestamp": "2018-04-09 20:28:00", "Yaw": -304.0503, "YPos": 3.492745412442804, "BuilderGridRelative": [{"Y": -2, "X": -3, "Z": 1, "Type": "cwc_minecraft_yellow_rn"}, {"Y": -2, "X": -1, "Z": 1, "Type": "cwc_minecraft_yellow_rn"}, {"Y": -2, "X": -3, "Z": 3, "Type": "cwc_minecraft_yellow_rn"}, {"Y": -2, "X": -1, "Z": 3, "Type": "cwc_minecraft_yellow_rn"}, {"Y": -1, "X": -3, "Z": 1, "Type": "cwc_minecraft_orange_rn"}, {"Y": -1, "X": -2, "Z": 1, "Type": "cwc_minecraft_orange_rn"}, {"Y": -1, "X": -1, "Z": 1, "Type": "cwc_minecraft_orange_rn"}, {"Y": -1, "X": -3, "Z": 2, "Type": "cwc_minecraft_orange_rn"}, {"Y": -1, "X": -2, "Z": 2, "Type": "cwc_minecraft_orange_rn"}, {"Y": -1, "X": -1, "Z": 2, "Type": "cwc_minecraft_orange_rn"}, {"Y": -1, "X": -3, "Z": 3, "Type": "cwc_minecraft_orange_rn"}, {"Y": -1, "X": -2, "Z": 3, "Type": "cwc_minecraft_orange_rn"}, {"Y": -1, "X": -1, "Z": 3, "Type": "cwc_minecraft_orange_rn"}], "DistanceTravelled": 4735, "BuilderInventory": [{"Index": 0, "Type": "cwc_minecraft_red_rn", "Quantity": 20}, {"Index": 1, "Type": "cwc_minecraft_orange_rn", "Quantity": 11}, {"Index": 2, "Type": "cwc_minecraft_yellow_rn", "Quantity": 16}, {"Index": 3, "Type": "cwc_minecraft_green_rn", "Quantity": 20}, {"Index": 4, "Type": "cwc_minecraft_blue_rn", "Quantity": 20}, {"Index": 5, "Type": "cwc_minecraft_purple_rn", "Quantity": 20}], "Pitch": 42.149986}, {"Timestamp": "2018-04-09 20:29:12", "Chat": ["<Architect> yes. now put 3 yellow blocks in a line on top of the orange"], "ScreenshotPath": "312333-Builder-chat.png"}, {"BuilderGridAbsolute": [{"Y": 1, "X": 0, "Z": 0, "Type": "cwc_minecraft_yellow_rn"}, {"Y": 1, "X": 2, "Z": 0, "Type": "cwc_minecraft_yellow_rn"}, {"Y": 1, "X": 0, "Z": 2, "Type": "cwc_minecraft_yellow_rn"}, {"Y": 1, "X": 2, "Z": 2, "Type": "cwc_minecraft_yellow_rn"}, {"Y": 2, "X": 0, "Z": 0, "Type": "cwc_minecraft_orange_rn"}, {"Y": 2, "X": 1, "Z": 0, "Type": "cwc_minecraft_orange_rn"}, {"Y": 2, "X": 2, "Z": 0, "Type": "cwc_minecraft_orange_rn"}, {"Y": 2, "X": 0, "Z": 1, "Type": "cwc_minecraft_orange_rn"}, {"Y": 2, "X": 1, "Z": 1, "Type": "cwc_minecraft_orange_rn"}, {"Y": 2, "X": 2, "Z": 1, "Type": "cwc_minecraft_orange_rn"}, {"Y": 2, "X": 0, "Z": 2, "Type": "cwc_minecraft_orange_rn"}, {"Y": 2, "X": 1, "Z": 2, "Type": "cwc_minecraft_orange_rn"}, {"Y": 2, "X": 2, "Z": 2, "Type": "cwc_minecraft_orange_rn"}], "XPos": 3.820968861964912, "TimeAlive": 6361, "ZPos": -0.4835701169625762, "Timestamp": "2018-04-09 20:29:12", "Yaw": -304.0503, "YPos": 3.492745412442804, "BuilderGridRelative": [{"Y": -2, "X": -3, "Z": 1, "Type": "cwc_minecraft_yellow_rn"}, {"Y": -2, "X": -1, "Z": 1, "Type": "cwc_minecraft_yellow_rn"}, {"Y": -2, "X": -3, "Z": 3, "Type": "cwc_minecraft_yellow_rn"}, {"Y": -2, "X": -1, "Z": 3, "Type": "cwc_minecraft_yellow_rn"}, {"Y": -1, "X": -3, "Z": 1, "Type": "cwc_minecraft_orange_rn"}, {"Y": -1, "X": -2, "Z": 1, "Type": "cwc_minecraft_orange_rn"}, {"Y": -1, "X": -1, "Z": 1, "Type": "cwc_minecraft_orange_rn"}, {"Y": -1, "X": -3, "Z": 2, "Type": "cwc_minecraft_orange_rn"}, {"Y": -1, "X": -2, "Z": 2, "Type": "cwc_minecraft_orange_rn"}, {"Y": -1, "X": -1, "Z": 2, "Type": "cwc_minecraft_orange_rn"}, {"Y": -1, "X": -3, "Z": 3, "Type": "cwc_minecraft_orange_rn"}, {"Y": -1, "X": -2, "Z": 3, "Type": "cwc_minecraft_orange_rn"}, {"Y": -1, "X": -1, "Z": 3, "Type": "cwc_minecraft_orange_rn"}], "DistanceTravelled": 4735, "BuilderInventory": [{"Index": 0, "Type": "cwc_minecraft_red_rn", "Quantity": 20}, {"Index": 1, "Type": "cwc_minecraft_orange_rn", "Quantity": 11}, {"Index": 2, "Type": "cwc_minecraft_yellow_rn", "Quantity": 16}, {"Index": 3, "Type": "cwc_minecraft_green_rn", "Quantity": 20}, {"Index": 4, "Type": "cwc_minecraft_blue_rn", "Quantity": 20}, {"Index": 5, "Type": "cwc_minecraft_purple_rn", "Quantity": 20}], "Pitch": 42.149986}, {"Timestamp": "2018-04-09 20:29:26", "Chat": ["<Builder> in a line down the middle of the square?"], "ScreenshotPath": "326681-Builder-chat.png"}, {"BuilderGridAbsolute": [{"Y": 1, "X": 0, "Z": 0, "Type": "cwc_minecraft_yellow_rn"}, {"Y": 1, "X": 2, "Z": 0, "Type": "cwc_minecraft_yellow_rn"}, {"Y": 1, "X": 0, "Z": 2, "Type": "cwc_minecraft_yellow_rn"}, {"Y": 1, "X": 2, "Z": 2, "Type": "cwc_minecraft_yellow_rn"}, {"Y": 2, "X": 0, "Z": 0, "Type": "cwc_minecraft_orange_rn"}, {"Y": 2, "X": 1, "Z": 0, "Type": "cwc_minecraft_orange_rn"}, {"Y": 2, "X": 2, "Z": 0, "Type": "cwc_minecraft_orange_rn"}, {"Y": 2, "X": 0, "Z": 1, "Type": "cwc_minecraft_orange_rn"}, {"Y": 2, "X": 1, "Z": 1, "Type": "cwc_minecraft_orange_rn"}, {"Y": 2, "X": 2, "Z": 1, "Type": "cwc_minecraft_orange_rn"}, {"Y": 2, "X": 0, "Z": 2, "Type": "cwc_minecraft_orange_rn"}, {"Y": 2, "X": 1, "Z": 2, "Type": "cwc_minecraft_orange_rn"}, {"Y": 2, "X": 2, "Z": 2, "Type": "cwc_minecraft_orange_rn"}], "XPos": 3.820968861964912, "TimeAlive": 6648, "ZPos": -0.4835701169625762, "Timestamp": "2018-04-09 20:29:26", "Yaw": -301.50034, "YPos": 3.492745412442804, "BuilderGridRelative": [{"Y": -2, "X": -3, "Z": 1, "Type": "cwc_minecraft_yellow_rn"}, {"Y": -2, "X": -1, "Z": 1, "Type": "cwc_minecraft_yellow_rn"}, {"Y": -2, "X": -3, "Z": 3, "Type": "cwc_minecraft_yellow_rn"}, {"Y": -2, "X": -1, "Z": 3, "Type": "cwc_minecraft_yellow_rn"}, {"Y": -1, "X": -3, "Z": 1, "Type": "cwc_minecraft_orange_rn"}, {"Y": -1, "X": -2, "Z": 1, "Type": "cwc_minecraft_orange_rn"}, {"Y": -1, "X": -1, "Z": 1, "Type": "cwc_minecraft_orange_rn"}, {"Y": -1, "X": -3, "Z": 2, "Type": "cwc_minecraft_orange_rn"}, {"Y": -1, "X": -2, "Z": 2, "Type": "cwc_minecraft_orange_rn"}, {"Y": -1, "X": -1, "Z": 2, "Type": "cwc_minecraft_orange_rn"}, {"Y": -1, "X": -3, "Z": 3, "Type": "cwc_minecraft_orange_rn"}, {"Y": -1, "X": -2, "Z": 3, "Type": "cwc_minecraft_orange_rn"}, {"Y": -1, "X": -1, "Z": 3, "Type": "cwc_minecraft_orange_rn"}], "DistanceTravelled": 4735, "BuilderInventory": [{"Index": 0, "Type": "cwc_minecraft_red_rn", "Quantity": 20}, {"Index": 1, "Type": "cwc_minecraft_orange_rn", "Quantity": 11}, {"Index": 2, "Type": "cwc_minecraft_yellow_rn", "Quantity": 16}, {"Index": 3, "Type": "cwc_minecraft_green_rn", "Quantity": 20}, {"Index": 4, "Type": "cwc_minecraft_blue_rn", "Quantity": 20}, {"Index": 5, "Type": "cwc_minecraft_purple_rn", "Quantity": 20}], "Pitch": 42.149986}, {"Timestamp": "2018-04-09 20:29:47", "Chat": ["<Architect> no along the edge"], "ScreenshotPath": "347429-Builder-chat.png"}, {"BuilderGridAbsolute": [{"Y": 1, "X": 0, "Z": 0, "Type": "cwc_minecraft_yellow_rn"}, {"Y": 1, "X": 2, "Z": 0, "Type": "cwc_minecraft_yellow_rn"}, {"Y": 1, "X": 0, "Z": 2, "Type": "cwc_minecraft_yellow_rn"}, {"Y": 1, "X": 2, "Z": 2, "Type": "cwc_minecraft_yellow_rn"}, {"Y": 2, "X": 0, "Z": 0, "Type": "cwc_minecraft_orange_rn"}, {"Y": 2, "X": 1, "Z": 0, "Type": "cwc_minecraft_orange_rn"}, {"Y": 2, "X": 2, "Z": 0, "Type": "cwc_minecraft_orange_rn"}, {"Y": 2, "X": 0, "Z": 1, "Type": "cwc_minecraft_orange_rn"}, {"Y": 2, "X": 1, "Z": 1, "Type": "cwc_minecraft_orange_rn"}, {"Y": 2, "X": 2, "Z": 1, "Type": "cwc_minecraft_orange_rn"}, {"Y": 2, "X": 0, "Z": 2, "Type": "cwc_minecraft_orange_rn"}, {"Y": 2, "X": 1, "Z": 2, "Type": "cwc_minecraft_orange_rn"}, {"Y": 2, "X": 2, "Z": 2, "Type": "cwc_minecraft_orange_rn"}], "XPos": 1.8410230044275453, "TimeAlive": 7063, "ZPos": -0.635235228383467, "Timestamp": "2018-04-09 20:29:47", "Yaw": -358.50018, "YPos": 3.492745412442804, "BuilderGridRelative": [{"Y": -2, "X": -1, "Z": 1, "Type": "cwc_minecraft_yellow_rn"}, {"Y": -2, "X": 1, "Z": 1, "Type": "cwc_minecraft_yellow_rn"}, {"Y": -2, "X": -1, "Z": 3, "Type": "cwc_minecraft_yellow_rn"}, {"Y": -2, "X": 1, "Z": 3, "Type": "cwc_minecraft_yellow_rn"}, {"Y": -1, "X": -1, "Z": 1, "Type": "cwc_minecraft_orange_rn"}, {"Y": -1, "X": 0, "Z": 1, "Type": "cwc_minecraft_orange_rn"}, {"Y": -1, "X": 1, "Z": 1, "Type": "cwc_minecraft_orange_rn"}, {"Y": -1, "X": -1, "Z": 2, "Type": "cwc_minecraft_orange_rn"}, {"Y": -1, "X": 0, "Z": 2, "Type": "cwc_minecraft_orange_rn"}, {"Y": -1, "X": 1, "Z": 2, "Type": "cwc_minecraft_orange_rn"}, {"Y": -1, "X": -1, "Z": 3, "Type": "cwc_minecraft_orange_rn"}, {"Y": -1, "X": 0, "Z": 3, "Type": "cwc_minecraft_orange_rn"}, {"Y": -1, "X": 1, "Z": 3, "Type": "cwc_minecraft_orange_rn"}], "DistanceTravelled": 4735, "BuilderInventory": [{"Index": 0, "Type": "cwc_minecraft_red_rn", "Quantity": 20}, {"Index": 1, "Type": "cwc_minecraft_orange_rn", "Quantity": 11}, {"Index": 2, "Type": "cwc_minecraft_yellow_rn", "Quantity": 16}, {"Index": 3, "Type": "cwc_minecraft_green_rn", "Quantity": 20}, {"Index": 4, "Type": "cwc_minecraft_blue_rn", "Quantity": 20}, {"Index": 5, "Type": "cwc_minecraft_purple_rn", "Quantity": 20}], "Pitch": 43.499958}, {"BuilderGridAbsolute": [{"Y": 1, "X": 0, "Z": 0, "Type": "cwc_minecraft_yellow_rn"}, {"Y": 1, "X": 2, "Z": 0, "Type": "cwc_minecraft_yellow_rn"}, {"Y": 1, "X": 0, "Z": 2, "Type": "cwc_minecraft_yellow_rn"}, {"Y": 1, "X": 2, "Z": 2, "Type": "cwc_minecraft_yellow_rn"}, {"Y": 2, "X": 0, "Z": 0, "Type": "cwc_minecraft_orange_rn"}, {"Y": 2, "X": 1, "Z": 0, "Type": "cwc_minecraft_orange_rn"}, {"Y": 2, "X": 2, "Z": 0, "Type": "cwc_minecraft_orange_rn"}, {"Y": 2, "X": 0, "Z": 1, "Type": "cwc_minecraft_orange_rn"}, {"Y": 2, "X": 1, "Z": 1, "Type": "cwc_minecraft_orange_rn"}, {"Y": 2, "X": 2, "Z": 1, "Type": "cwc_minecraft_orange_rn"}, {"Y": 2, "X": 0, "Z": 2, "Type": "cwc_minecraft_orange_rn"}, {"Y": 2, "X": 1, "Z": 2, "Type": "cwc_minecraft_orange_rn"}, {"Y": 2, "X": 2, "Z": 2, "Type": "cwc_minecraft_orange_rn"}, {"Y": 3, "X": 2, "Z": 2, "Type": "cwc_minecraft_yellow_rn"}], "XPos": 2.8946765560573846, "TimeAlive": 7140, "ZPos": -0.6326611210066084, "Timestamp": "2018-04-09 20:29:51", "Yaw": -354.45023, "YPos": 3.492745412442804, "ScreenshotPath": "351329-Builder-putdown.png", "BuilderGridRelative": [{"Y": -2, "X": -2, "Z": 1, "Type": "cwc_minecraft_yellow_rn"}, {"Y": -2, "X": 0, "Z": 1, "Type": "cwc_minecraft_yellow_rn"}, {"Y": -2, "X": -2, "Z": 3, "Type": "cwc_minecraft_yellow_rn"}, {"Y": -2, "X": 0, "Z": 3, "Type": "cwc_minecraft_yellow_rn"}, {"Y": -1, "X": -2, "Z": 1, "Type": "cwc_minecraft_orange_rn"}, {"Y": -1, "X": -1, "Z": 1, "Type": "cwc_minecraft_orange_rn"}, {"Y": -1, "X": 0, "Z": 1, "Type": "cwc_minecraft_orange_rn"}, {"Y": -1, "X": -2, "Z": 2, "Type": "cwc_minecraft_orange_rn"}, {"Y": -1, "X": -1, "Z": 2, "Type": "cwc_minecraft_orange_rn"}, {"Y": -1, "X": 0, "Z": 2, "Type": "cwc_minecraft_orange_rn"}, {"Y": -1, "X": -2, "Z": 3, "Type": "cwc_minecraft_orange_rn"}, {"Y": -1, "X": -1, "Z": 3, "Type": "cwc_minecraft_orange_rn"}, {"Y": -1, "X": 0, "Z": 3, "Type": "cwc_minecraft_orange_rn"}, {"Y": 0, "X": 0, "Z": 3, "Type": "cwc_minecraft_yellow_rn"}], "DistanceTravelled": 4735, "BuilderInventory": [{"Index": 0, "Type": "cwc_minecraft_red_rn", "Quantity": 20}, {"Index": 1, "Type": "cwc_minecraft_orange_rn", "Quantity": 11}, {"Index": 2, "Type": "cwc_minecraft_yellow_rn", "Quantity": 15}, {"Index": 3, "Type": "cwc_minecraft_green_rn", "Quantity": 20}, {"Index": 4, "Type": "cwc_minecraft_blue_rn", "Quantity": 20}, {"Index": 5, "Type": "cwc_minecraft_purple_rn", "Quantity": 20}], "Pitch": 34.499966}, {"BuilderGridAbsolute": [{"Y": 1, "X": 0, "Z": 0, "Type": "cwc_minecraft_yellow_rn"}, {"Y": 1, "X": 2, "Z": 0, "Type": "cwc_minecraft_yellow_rn"}, {"Y": 1, "X": 0, "Z": 2, "Type": "cwc_minecraft_yellow_rn"}, {"Y": 1, "X": 2, "Z": 2, "Type": "cwc_minecraft_yellow_rn"}, {"Y": 2, "X": 0, "Z": 0, "Type": "cwc_minecraft_orange_rn"}, {"Y": 2, "X": 1, "Z": 0, "Type": "cwc_minecraft_orange_rn"}, {"Y": 2, "X": 2, "Z": 0, "Type": "cwc_minecraft_orange_rn"}, {"Y": 2, "X": 0, "Z": 1, "Type": "cwc_minecraft_orange_rn"}, {"Y": 2, "X": 1, "Z": 1, "Type": "cwc_minecraft_orange_rn"}, {"Y": 2, "X": 2, "Z": 1, "Type": "cwc_minecraft_orange_rn"}, {"Y": 2, "X": 0, "Z": 2, "Type": "cwc_minecraft_orange_rn"}, {"Y": 2, "X": 1, "Z": 2, "Type": "cwc_minecraft_orange_rn"}, {"Y": 2, "X": 2, "Z": 2, "Type": "cwc_minecraft_orange_rn"}, {"Y": 3, "X": 2, "Z": 1, "Type": "cwc_minecraft_yellow_rn"}, {"Y": 3, "X": 2, "Z": 2, "Type": "cwc_minecraft_yellow_rn"}], "XPos": 2.8978139581966955, "TimeAlive": 7166, "ZPos": -0.6326611210066084, "Timestamp": "2018-04-09 20:29:52", "Yaw": -350.85028, "YPos": 3.492745412442804, "ScreenshotPath": "352627-Builder-putdown.png", "BuilderGridRelative": [{"Y": -2, "X": -2, "Z": 1, "Type": "cwc_minecraft_yellow_rn"}, {"Y": -2, "X": 0, "Z": 1, "Type": "cwc_minecraft_yellow_rn"}, {"Y": -2, "X": -2, "Z": 3, "Type": "cwc_minecraft_yellow_rn"}, {"Y": -2, "X": 0, "Z": 3, "Type": "cwc_minecraft_yellow_rn"}, {"Y": -1, "X": -2, "Z": 1, "Type": "cwc_minecraft_orange_rn"}, {"Y": -1, "X": -1, "Z": 1, "Type": "cwc_minecraft_orange_rn"}, {"Y": -1, "X": 0, "Z": 1, "Type": "cwc_minecraft_orange_rn"}, {"Y": -1, "X": -2, "Z": 2, "Type": "cwc_minecraft_orange_rn"}, {"Y": -1, "X": -1, "Z": 2, "Type": "cwc_minecraft_orange_rn"}, {"Y": -1, "X": 0, "Z": 2, "Type": "cwc_minecraft_orange_rn"}, {"Y": -1, "X": -2, "Z": 3, "Type": "cwc_minecraft_orange_rn"}, {"Y": -1, "X": -1, "Z": 3, "Type": "cwc_minecraft_orange_rn"}, {"Y": -1, "X": 0, "Z": 3, "Type": "cwc_minecraft_orange_rn"}, {"Y": 0, "X": 0, "Z": 2, "Type": "cwc_minecraft_yellow_rn"}, {"Y": 0, "X": 0, "Z": 3, "Type": "cwc_minecraft_yellow_rn"}], "DistanceTravelled": 4735, "BuilderInventory": [{"Index": 0, "Type": "cwc_minecraft_red_rn", "Quantity": 20}, {"Index": 1, "Type": "cwc_minecraft_orange_rn", "Quantity": 11}, {"Index": 2, "Type": "cwc_minecraft_yellow_rn", "Quantity": 14}, {"Index": 3, "Type": "cwc_minecraft_green_rn", "Quantity": 20}, {"Index": 4, "Type": "cwc_minecraft_blue_rn", "Quantity": 20}, {"Index": 5, "Type": "cwc_minecraft_purple_rn", "Quantity": 20}], "Pitch": 46.79996}, {"BuilderGridAbsolute": [{"Y": 1, "X": 0, "Z": 0, "Type": "cwc_minecraft_yellow_rn"}, {"Y": 1, "X": 2, "Z": 0, "Type": "cwc_minecraft_yellow_rn"}, {"Y": 1, "X": 0, "Z": 2, "Type": "cwc_minecraft_yellow_rn"}, {"Y": 1, "X": 2, "Z": 2, "Type": "cwc_minecraft_yellow_rn"}, {"Y": 2, "X": 0, "Z": 0, "Type": "cwc_minecraft_orange_rn"}, {"Y": 2, "X": 1, "Z": 0, "Type": "cwc_minecraft_orange_rn"}, {"Y": 2, "X": 2, "Z": 0, "Type": "cwc_minecraft_orange_rn"}, {"Y": 2, "X": 0, "Z": 1, "Type": "cwc_minecraft_orange_rn"}, {"Y": 2, "X": 1, "Z": 1, "Type": "cwc_minecraft_orange_rn"}, {"Y": 2, "X": 2, "Z": 1, "Type": "cwc_minecraft_orange_rn"}, {"Y": 2, "X": 0, "Z": 2, "Type": "cwc_minecraft_orange_rn"}, {"Y": 2, "X": 1, "Z": 2, "Type": "cwc_minecraft_orange_rn"}, {"Y": 2, "X": 2, "Z": 2, "Type": "cwc_minecraft_orange_rn"}, {"Y": 3, "X": 2, "Z": 0, "Type": "cwc_minecraft_yellow_rn"}, {"Y": 3, "X": 2, "Z": 1, "Type": "cwc_minecraft_yellow_rn"}, {"Y": 3, "X": 2, "Z": 2, "Type": "cwc_minecraft_yellow_rn"}], "XPos": 2.8978139581966955, "TimeAlive": 7188, "ZPos": -0.6326611210066084, "Timestamp": "2018-04-09 20:29:53", "Yaw": -348.60028, "YPos": 3.492745412442804, "ScreenshotPath": "353727-Builder-putdown.png", "BuilderGridRelative": [{"Y": -2, "X": -2, "Z": 1, "Type": "cwc_minecraft_yellow_rn"}, {"Y": -2, "X": 0, "Z": 1, "Type": "cwc_minecraft_yellow_rn"}, {"Y": -2, "X": -2, "Z": 3, "Type": "cwc_minecraft_yellow_rn"}, {"Y": -2, "X": 0, "Z": 3, "Type": "cwc_minecraft_yellow_rn"}, {"Y": -1, "X": -2, "Z": 1, "Type": "cwc_minecraft_orange_rn"}, {"Y": -1, "X": -1, "Z": 1, "Type": "cwc_minecraft_orange_rn"}, {"Y": -1, "X": 0, "Z": 1, "Type": "cwc_minecraft_orange_rn"}, {"Y": -1, "X": -2, "Z": 2, "Type": "cwc_minecraft_orange_rn"}, {"Y": -1, "X": -1, "Z": 2, "Type": "cwc_minecraft_orange_rn"}, {"Y": -1, "X": 0, "Z": 2, "Type": "cwc_minecraft_orange_rn"}, {"Y": -1, "X": -2, "Z": 3, "Type": "cwc_minecraft_orange_rn"}, {"Y": -1, "X": -1, "Z": 3, "Type": "cwc_minecraft_orange_rn"}, {"Y": -1, "X": 0, "Z": 3, "Type": "cwc_minecraft_orange_rn"}, {"Y": 0, "X": 0, "Z": 1, "Type": "cwc_minecraft_yellow_rn"}, {"Y": 0, "X": 0, "Z": 2, "Type": "cwc_minecraft_yellow_rn"}, {"Y": 0, "X": 0, "Z": 3, "Type": "cwc_minecraft_yellow_rn"}], "DistanceTravelled": 4735, "BuilderInventory": [{"Index": 0, "Type": "cwc_minecraft_red_rn", "Quantity": 20}, {"Index": 1, "Type": "cwc_minecraft_orange_rn", "Quantity": 11}, {"Index": 2, "Type": "cwc_minecraft_yellow_rn", "Quantity": 13}, {"Index": 3, "Type": "cwc_minecraft_green_rn", "Quantity": 20}, {"Index": 4, "Type": "cwc_minecraft_blue_rn", "Quantity": 20}, {"Index": 5, "Type": "cwc_minecraft_purple_rn", "Quantity": 20}], "Pitch": 60.149963}, {"Timestamp": "2018-04-09 20:29:58", "Chat": ["<Builder> like that?"], "ScreenshotPath": "358425-Builder-chat.png"}, {"BuilderGridAbsolute": [{"Y": 1, "X": 0, "Z": 0, "Type": "cwc_minecraft_yellow_rn"}, {"Y": 1, "X": 2, "Z": 0, "Type": "cwc_minecraft_yellow_rn"}, {"Y": 1, "X": 0, "Z": 2, "Type": "cwc_minecraft_yellow_rn"}, {"Y": 1, "X": 2, "Z": 2, "Type": "cwc_minecraft_yellow_rn"}, {"Y": 2, "X": 0, "Z": 0, "Type": "cwc_minecraft_orange_rn"}, {"Y": 2, "X": 1, "Z": 0, "Type": "cwc_minecraft_orange_rn"}, {"Y": 2, "X": 2, "Z": 0, "Type": "cwc_minecraft_orange_rn"}, {"Y": 2, "X": 0, "Z": 1, "Type": "cwc_minecraft_orange_rn"}, {"Y": 2, "X": 1, "Z": 1, "Type": "cwc_minecraft_orange_rn"}, {"Y": 2, "X": 2, "Z": 1, "Type": "cwc_minecraft_orange_rn"}, {"Y": 2, "X": 0, "Z": 2, "Type": "cwc_minecraft_orange_rn"}, {"Y": 2, "X": 1, "Z": 2, "Type": "cwc_minecraft_orange_rn"}, {"Y": 2, "X": 2, "Z": 2, "Type": "cwc_minecraft_orange_rn"}, {"Y": 3, "X": 2, "Z": 0, "Type": "cwc_minecraft_yellow_rn"}, {"Y": 3, "X": 2, "Z": 1, "Type": "cwc_minecraft_yellow_rn"}, {"Y": 3, "X": 2, "Z": 2, "Type": "cwc_minecraft_yellow_rn"}], "XPos": 2.8978139581966955, "TimeAlive": 7283, "ZPos": -0.6326611210066084, "Timestamp": "2018-04-09 20:29:58", "Yaw": -325.8003, "YPos": 3.492745412442804, "BuilderGridRelative": [{"Y": -2, "X": -2, "Z": 1, "Type": "cwc_minecraft_yellow_rn"}, {"Y": -2, "X": 0, "Z": 1, "Type": "cwc_minecraft_yellow_rn"}, {"Y": -2, "X": -2, "Z": 3, "Type": "cwc_minecraft_yellow_rn"}, {"Y": -2, "X": 0, "Z": 3, "Type": "cwc_minecraft_yellow_rn"}, {"Y": -1, "X": -2, "Z": 1, "Type": "cwc_minecraft_orange_rn"}, {"Y": -1, "X": -1, "Z": 1, "Type": "cwc_minecraft_orange_rn"}, {"Y": -1, "X": 0, "Z": 1, "Type": "cwc_minecraft_orange_rn"}, {"Y": -1, "X": -2, "Z": 2, "Type": "cwc_minecraft_orange_rn"}, {"Y": -1, "X": -1, "Z": 2, "Type": "cwc_minecraft_orange_rn"}, {"Y": -1, "X": 0, "Z": 2, "Type": "cwc_minecraft_orange_rn"}, {"Y": -1, "X": -2, "Z": 3, "Type": "cwc_minecraft_orange_rn"}, {"Y": -1, "X": -1, "Z": 3, "Type": "cwc_minecraft_orange_rn"}, {"Y": -1, "X": 0, "Z": 3, "Type": "cwc_minecraft_orange_rn"}, {"Y": 0, "X": 0, "Z": 1, "Type": "cwc_minecraft_yellow_rn"}, {"Y": 0, "X": 0, "Z": 2, "Type": "cwc_minecraft_yellow_rn"}, {"Y": 0, "X": 0, "Z": 3, "Type": "cwc_minecraft_yellow_rn"}], "DistanceTravelled": 4735, "BuilderInventory": [{"Index": 0, "Type": "cwc_minecraft_red_rn", "Quantity": 20}, {"Index": 1, "Type": "cwc_minecraft_orange_rn", "Quantity": 11}, {"Index": 2, "Type": "cwc_minecraft_yellow_rn", "Quantity": 13}, {"Index": 3, "Type": "cwc_minecraft_green_rn", "Quantity": 20}, {"Index": 4, "Type": "cwc_minecraft_blue_rn", "Quantity": 20}, {"Index": 5, "Type": "cwc_minecraft_purple_rn", "Quantity": 20}], "Pitch": 46.949966}, {"Timestamp": "2018-04-09 20:30:18", "Chat": ["<Architect> yes. now put 3 more yellow blocks on top of those"], "ScreenshotPath": "379190-Builder-chat.png"}, {"BuilderGridAbsolute": [{"Y": 1, "X": 0, "Z": 0, "Type": "cwc_minecraft_yellow_rn"}, {"Y": 1, "X": 2, "Z": 0, "Type": "cwc_minecraft_yellow_rn"}, {"Y": 1, "X": 0, "Z": 2, "Type": "cwc_minecraft_yellow_rn"}, {"Y": 1, "X": 2, "Z": 2, "Type": "cwc_minecraft_yellow_rn"}, {"Y": 2, "X": 0, "Z": 0, "Type": "cwc_minecraft_orange_rn"}, {"Y": 2, "X": 1, "Z": 0, "Type": "cwc_minecraft_orange_rn"}, {"Y": 2, "X": 2, "Z": 0, "Type": "cwc_minecraft_orange_rn"}, {"Y": 2, "X": 0, "Z": 1, "Type": "cwc_minecraft_orange_rn"}, {"Y": 2, "X": 1, "Z": 1, "Type": "cwc_minecraft_orange_rn"}, {"Y": 2, "X": 2, "Z": 1, "Type": "cwc_minecraft_orange_rn"}, {"Y": 2, "X": 0, "Z": 2, "Type": "cwc_minecraft_orange_rn"}, {"Y": 2, "X": 1, "Z": 2, "Type": "cwc_minecraft_orange_rn"}, {"Y": 2, "X": 2, "Z": 2, "Type": "cwc_minecraft_orange_rn"}, {"Y": 3, "X": 2, "Z": 0, "Type": "cwc_minecraft_yellow_rn"}, {"Y": 3, "X": 2, "Z": 1, "Type": "cwc_minecraft_yellow_rn"}, {"Y": 3, "X": 2, "Z": 2, "Type": "cwc_minecraft_yellow_rn"}], "XPos": 0.7435014705918104, "TimeAlive": 7698, "ZPos": -2.096754562926357, "Timestamp": "2018-04-09 20:30:18", "Yaw": -325.8003, "YPos": 3.492745412442804, "BuilderGridRelative": [{"Y": -2, "X": 0, "Z": 3, "Type": "cwc_minecraft_yellow_rn"}, {"Y": -2, "X": 2, "Z": 3, "Type": "cwc_minecraft_yellow_rn"}, {"Y": -2, "X": 0, "Z": 5, "Type": "cwc_minecraft_yellow_rn"}, {"Y": -2, "X": 2, "Z": 5, "Type": "cwc_minecraft_yellow_rn"}, {"Y": -1, "X": 0, "Z": 3, "Type": "cwc_minecraft_orange_rn"}, {"Y": -1, "X": 1, "Z": 3, "Type": "cwc_minecraft_orange_rn"}, {"Y": -1, "X": 2, "Z": 3, "Type": "cwc_minecraft_orange_rn"}, {"Y": -1, "X": 0, "Z": 4, "Type": "cwc_minecraft_orange_rn"}, {"Y": -1, "X": 1, "Z": 4, "Type": "cwc_minecraft_orange_rn"}, {"Y": -1, "X": 2, "Z": 4, "Type": "cwc_minecraft_orange_rn"}, {"Y": -1, "X": 0, "Z": 5, "Type": "cwc_minecraft_orange_rn"}, {"Y": -1, "X": 1, "Z": 5, "Type": "cwc_minecraft_orange_rn"}, {"Y": -1, "X": 2, "Z": 5, "Type": "cwc_minecraft_orange_rn"}, {"Y": 0, "X": 2, "Z": 3, "Type": "cwc_minecraft_yellow_rn"}, {"Y": 0, "X": 2, "Z": 4, "Type": "cwc_minecraft_yellow_rn"}, {"Y": 0, "X": 2, "Z": 5, "Type": "cwc_minecraft_yellow_rn"}], "DistanceTravelled": 4735, "BuilderInventory": [{"Index": 0, "Type": "cwc_minecraft_red_rn", "Quantity": 20}, {"Index": 1, "Type": "cwc_minecraft_orange_rn", "Quantity": 11}, {"Index": 2, "Type": "cwc_minecraft_yellow_rn", "Quantity": 13}, {"Index": 3, "Type": "cwc_minecraft_green_rn", "Quantity": 20}, {"Index": 4, "Type": "cwc_minecraft_blue_rn", "Quantity": 20}, {"Index": 5, "Type": "cwc_minecraft_purple_rn", "Quantity": 20}], "Pitch": 46.949966}, {"BuilderGridAbsolute": [{"Y": 1, "X": 0, "Z": 0, "Type": "cwc_minecraft_yellow_rn"}, {"Y": 1, "X": 2, "Z": 0, "Type": "cwc_minecraft_yellow_rn"}, {"Y": 1, "X": 0, "Z": 2, "Type": "cwc_minecraft_yellow_rn"}, {"Y": 1, "X": 2, "Z": 2, "Type": "cwc_minecraft_yellow_rn"}, {"Y": 2, "X": 0, "Z": 0, "Type": "cwc_minecraft_orange_rn"}, {"Y": 2, "X": 1, "Z": 0, "Type": "cwc_minecraft_orange_rn"}, {"Y": 2, "X": 2, "Z": 0, "Type": "cwc_minecraft_orange_rn"}, {"Y": 2, "X": 0, "Z": 1, "Type": "cwc_minecraft_orange_rn"}, {"Y": 2, "X": 1, "Z": 1, "Type": "cwc_minecraft_orange_rn"}, {"Y": 2, "X": 2, "Z": 1, "Type": "cwc_minecraft_orange_rn"}, {"Y": 2, "X": 0, "Z": 2, "Type": "cwc_minecraft_orange_rn"}, {"Y": 2, "X": 1, "Z": 2, "Type": "cwc_minecraft_orange_rn"}, {"Y": 2, "X": 2, "Z": 2, "Type": "cwc_minecraft_orange_rn"}, {"Y": 3, "X": 2, "Z": 0, "Type": "cwc_minecraft_yellow_rn"}, {"Y": 3, "X": 2, "Z": 1, "Type": "cwc_minecraft_yellow_rn"}, {"Y": 3, "X": 2, "Z": 2, "Type": "cwc_minecraft_yellow_rn"}, {"Y": 4, "X": 2, "Z": 0, "Type": "cwc_minecraft_yellow_rn"}], "XPos": 1.9453028339917482, "TimeAlive": 7768, "ZPos": -1.289701322436105, "Timestamp": "2018-04-09 20:30:22", "Yaw": -17.85025, "YPos": 3.492745412442804, "ScreenshotPath": "382742-Builder-putdown.png", "BuilderGridRelative": [{"Y": -2, "X": -1, "Z": 2, "Type": "cwc_minecraft_yellow_rn"}, {"Y": -2, "X": 1, "Z": 2, "Type": "cwc_minecraft_yellow_rn"}, {"Y": -2, "X": -1, "Z": 4, "Type": "cwc_minecraft_yellow_rn"}, {"Y": -2, "X": 1, "Z": 4, "Type": "cwc_minecraft_yellow_rn"}, {"Y": -1, "X": -1, "Z": 2, "Type": "cwc_minecraft_orange_rn"}, {"Y": -1, "X": 0, "Z": 2, "Type": "cwc_minecraft_orange_rn"}, {"Y": -1, "X": 1, "Z": 2, "Type": "cwc_minecraft_orange_rn"}, {"Y": -1, "X": -1, "Z": 3, "Type": "cwc_minecraft_orange_rn"}, {"Y": -1, "X": 0, "Z": 3, "Type": "cwc_minecraft_orange_rn"}, {"Y": -1, "X": 1, "Z": 3, "Type": "cwc_minecraft_orange_rn"}, {"Y": -1, "X": -1, "Z": 4, "Type": "cwc_minecraft_orange_rn"}, {"Y": -1, "X": 0, "Z": 4, "Type": "cwc_minecraft_orange_rn"}, {"Y": -1, "X": 1, "Z": 4, "Type": "cwc_minecraft_orange_rn"}, {"Y": 0, "X": 1, "Z": 2, "Type": "cwc_minecraft_yellow_rn"}, {"Y": 0, "X": 1, "Z": 3, "Type": "cwc_minecraft_yellow_rn"}, {"Y": 0, "X": 1, "Z": 4, "Type": "cwc_minecraft_yellow_rn"}, {"Y": 1, "X": 1, "Z": 2, "Type": "cwc_minecraft_yellow_rn"}], "DistanceTravelled": 4735, "BuilderInventory": [{"Index": 0, "Type": "cwc_minecraft_red_rn", "Quantity": 20}, {"Index": 1, "Type": "cwc_minecraft_orange_rn", "Quantity": 11}, {"Index": 2, "Type": "cwc_minecraft_yellow_rn", "Quantity": 12}, {"Index": 3, "Type": "cwc_minecraft_green_rn", "Quantity": 20}, {"Index": 4, "Type": "cwc_minecraft_blue_rn", "Quantity": 20}, {"Index": 5, "Type": "cwc_minecraft_purple_rn", "Quantity": 20}], "Pitch": 34.64996}, {"BuilderGridAbsolute": [{"Y": 1, "X": 0, "Z": 0, "Type": "cwc_minecraft_yellow_rn"}, {"Y": 1, "X": 2, "Z": 0, "Type": "cwc_minecraft_yellow_rn"}, {"Y": 1, "X": 0, "Z": 2, "Type": "cwc_minecraft_yellow_rn"}, {"Y": 1, "X": 2, "Z": 2, "Type": "cwc_minecraft_yellow_rn"}, {"Y": 2, "X": 0, "Z": 0, "Type": "cwc_minecraft_orange_rn"}, {"Y": 2, "X": 1, "Z": 0, "Type": "cwc_minecraft_orange_rn"}, {"Y": 2, "X": 2, "Z": 0, "Type": "cwc_minecraft_orange_rn"}, {"Y": 2, "X": 0, "Z": 1, "Type": "cwc_minecraft_orange_rn"}, {"Y": 2, "X": 1, "Z": 1, "Type": "cwc_minecraft_orange_rn"}, {"Y": 2, "X": 2, "Z": 1, "Type": "cwc_minecraft_orange_rn"}, {"Y": 2, "X": 0, "Z": 2, "Type": "cwc_minecraft_orange_rn"}, {"Y": 2, "X": 1, "Z": 2, "Type": "cwc_minecraft_orange_rn"}, {"Y": 2, "X": 2, "Z": 2, "Type": "cwc_minecraft_orange_rn"}, {"Y": 3, "X": 2, "Z": 0, "Type": "cwc_minecraft_yellow_rn"}, {"Y": 3, "X": 2, "Z": 1, "Type": "cwc_minecraft_yellow_rn"}, {"Y": 3, "X": 2, "Z": 2, "Type": "cwc_minecraft_yellow_rn"}, {"Y": 4, "X": 2, "Z": 0, "Type": "cwc_minecraft_yellow_rn"}, {"Y": 4, "X": 2, "Z": 1, "Type": "cwc_minecraft_yellow_rn"}], "XPos": -0.48393040379794316, "TimeAlive": 7843, "ZPos": 0.4011602178291278, "Timestamp": "2018-04-09 20:30:26", "Yaw": -62.55017, "YPos": 3.492745412442804, "ScreenshotPath": "386488-Builder-putdown.png", "BuilderGridRelative": [{"Y": -2, "X": 1, "Z": 0, "Type": "cwc_minecraft_yellow_rn"}, {"Y": -2, "X": 3, "Z": 0, "Type": "cwc_minecraft_yellow_rn"}, {"Y": -2, "X": 1, "Z": 2, "Type": "cwc_minecraft_yellow_rn"}, {"Y": -2, "X": 3, "Z": 2, "Type": "cwc_minecraft_yellow_rn"}, {"Y": -1, "X": 1, "Z": 0, "Type": "cwc_minecraft_orange_rn"}, {"Y": -1, "X": 2, "Z": 0, "Type": "cwc_minecraft_orange_rn"}, {"Y": -1, "X": 3, "Z": 0, "Type": "cwc_minecraft_orange_rn"}, {"Y": -1, "X": 1, "Z": 1, "Type": "cwc_minecraft_orange_rn"}, {"Y": -1, "X": 2, "Z": 1, "Type": "cwc_minecraft_orange_rn"}, {"Y": -1, "X": 3, "Z": 1, "Type": "cwc_minecraft_orange_rn"}, {"Y": -1, "X": 1, "Z": 2, "Type": "cwc_minecraft_orange_rn"}, {"Y": -1, "X": 2, "Z": 2, "Type": "cwc_minecraft_orange_rn"}, {"Y": -1, "X": 3, "Z": 2, "Type": "cwc_minecraft_orange_rn"}, {"Y": 0, "X": 3, "Z": 0, "Type": "cwc_minecraft_yellow_rn"}, {"Y": 0, "X": 3, "Z": 1, "Type": "cwc_minecraft_yellow_rn"}, {"Y": 0, "X": 3, "Z": 2, "Type": "cwc_minecraft_yellow_rn"}, {"Y": 1, "X": 3, "Z": 0, "Type": "cwc_minecraft_yellow_rn"}, {"Y": 1, "X": 3, "Z": 1, "Type": "cwc_minecraft_yellow_rn"}], "DistanceTravelled": 4735, "BuilderInventory": [{"Index": 0, "Type": "cwc_minecraft_red_rn", "Quantity": 20}, {"Index": 1, "Type": "cwc_minecraft_orange_rn", "Quantity": 11}, {"Index": 2, "Type": "cwc_minecraft_yellow_rn", "Quantity": 11}, {"Index": 3, "Type": "cwc_minecraft_green_rn", "Quantity": 20}, {"Index": 4, "Type": "cwc_minecraft_blue_rn", "Quantity": 20}, {"Index": 5, "Type": "cwc_minecraft_purple_rn", "Quantity": 20}], "Pitch": 18.599957}, {"BuilderGridAbsolute": [{"Y": 1, "X": 0, "Z": 0, "Type": "cwc_minecraft_yellow_rn"}, {"Y": 1, "X": 2, "Z": 0, "Type": "cwc_minecraft_yellow_rn"}, {"Y": 1, "X": 0, "Z": 2, "Type": "cwc_minecraft_yellow_rn"}, {"Y": 1, "X": 2, "Z": 2, "Type": "cwc_minecraft_yellow_rn"}, {"Y": 2, "X": 0, "Z": 0, "Type": "cwc_minecraft_orange_rn"}, {"Y": 2, "X": 1, "Z": 0, "Type": "cwc_minecraft_orange_rn"}, {"Y": 2, "X": 2, "Z": 0, "Type": "cwc_minecraft_orange_rn"}, {"Y": 2, "X": 0, "Z": 1, "Type": "cwc_minecraft_orange_rn"}, {"Y": 2, "X": 1, "Z": 1, "Type": "cwc_minecraft_orange_rn"}, {"Y": 2, "X": 2, "Z": 1, "Type": "cwc_minecraft_orange_rn"}, {"Y": 2, "X": 0, "Z": 2, "Type": "cwc_minecraft_orange_rn"}, {"Y": 2, "X": 1, "Z": 2, "Type": "cwc_minecraft_orange_rn"}, {"Y": 2, "X": 2, "Z": 2, "Type": "cwc_minecraft_orange_rn"}, {"Y": 3, "X": 2, "Z": 0, "Type": "cwc_minecraft_yellow_rn"}, {"Y": 3, "X": 2, "Z": 1, "Type": "cwc_minecraft_yellow_rn"}, {"Y": 3, "X": 2, "Z": 2, "Type": "cwc_minecraft_yellow_rn"}, {"Y": 4, "X": 2, "Z": 0, "Type": "cwc_minecraft_yellow_rn"}, {"Y": 4, "X": 2, "Z": 1, "Type": "cwc_minecraft_yellow_rn"}, {"Y": 4, "X": 2, "Z": 2, "Type": "cwc_minecraft_yellow_rn"}], "XPos": -0.48393040379794316, "TimeAlive": 7869, "ZPos": 0.5055698719632631, "Timestamp": "2018-04-09 20:30:27", "Yaw": -51.60019, "YPos": 3.492745412442804, "ScreenshotPath": "387788-Builder-putdown.png", "BuilderGridRelative": [{"Y": -2, "X": 1, "Z": 0, "Type": "cwc_minecraft_yellow_rn"}, {"Y": -2, "X": 3, "Z": 0, "Type": "cwc_minecraft_yellow_rn"}, {"Y": -2, "X": 1, "Z": 2, "Type": "cwc_minecraft_yellow_rn"}, {"Y": -2, "X": 3, "Z": 2, "Type": "cwc_minecraft_yellow_rn"}, {"Y": -1, "X": 1, "Z": 0, "Type": "cwc_minecraft_orange_rn"}, {"Y": -1, "X": 2, "Z": 0, "Type": "cwc_minecraft_orange_rn"}, {"Y": -1, "X": 3, "Z": 0, "Type": "cwc_minecraft_orange_rn"}, {"Y": -1, "X": 1, "Z": 1, "Type": "cwc_minecraft_orange_rn"}, {"Y": -1, "X": 2, "Z": 1, "Type": "cwc_minecraft_orange_rn"}, {"Y": -1, "X": 3, "Z": 1, "Type": "cwc_minecraft_orange_rn"}, {"Y": -1, "X": 1, "Z": 2, "Type": "cwc_minecraft_orange_rn"}, {"Y": -1, "X": 2, "Z": 2, "Type": "cwc_minecraft_orange_rn"}, {"Y": -1, "X": 3, "Z": 2, "Type": "cwc_minecraft_orange_rn"}, {"Y": 0, "X": 3, "Z": 0, "Type": "cwc_minecraft_yellow_rn"}, {"Y": 0, "X": 3, "Z": 1, "Type": "cwc_minecraft_yellow_rn"}, {"Y": 0, "X": 3, "Z": 2, "Type": "cwc_minecraft_yellow_rn"}, {"Y": 1, "X": 3, "Z": 0, "Type": "cwc_minecraft_yellow_rn"}, {"Y": 1, "X": 3, "Z": 1, "Type": "cwc_minecraft_yellow_rn"}, {"Y": 1, "X": 3, "Z": 2, "Type": "cwc_minecraft_yellow_rn"}], "DistanceTravelled": 4735, "BuilderInventory": [{"Index": 0, "Type": "cwc_minecraft_red_rn", "Quantity": 20}, {"Index": 1, "Type": "cwc_minecraft_orange_rn", "Quantity": 11}, {"Index": 2, "Type": "cwc_minecraft_yellow_rn", "Quantity": 10}, {"Index": 3, "Type": "cwc_minecraft_green_rn", "Quantity": 20}, {"Index": 4, "Type": "cwc_minecraft_blue_rn", "Quantity": 20}, {"Index": 5, "Type": "cwc_minecraft_purple_rn", "Quantity": 20}], "Pitch": 17.849958}, {"Timestamp": "2018-04-09 20:30:31", "Chat": ["<Builder> ok"], "ScreenshotPath": "392338-Builder-chat.png"}, {"BuilderGridAbsolute": [{"Y": 1, "X": 0, "Z": 0, "Type": "cwc_minecraft_yellow_rn"}, {"Y": 1, "X": 2, "Z": 0, "Type": "cwc_minecraft_yellow_rn"}, {"Y": 1, "X": 0, "Z": 2, "Type": "cwc_minecraft_yellow_rn"}, {"Y": 1, "X": 2, "Z": 2, "Type": "cwc_minecraft_yellow_rn"}, {"Y": 2, "X": 0, "Z": 0, "Type": "cwc_minecraft_orange_rn"}, {"Y": 2, "X": 1, "Z": 0, "Type": "cwc_minecraft_orange_rn"}, {"Y": 2, "X": 2, "Z": 0, "Type": "cwc_minecraft_orange_rn"}, {"Y": 2, "X": 0, "Z": 1, "Type": "cwc_minecraft_orange_rn"}, {"Y": 2, "X": 1, "Z": 1, "Type": "cwc_minecraft_orange_rn"}, {"Y": 2, "X": 2, "Z": 1, "Type": "cwc_minecraft_orange_rn"}, {"Y": 2, "X": 0, "Z": 2, "Type": "cwc_minecraft_orange_rn"}, {"Y": 2, "X": 1, "Z": 2, "Type": "cwc_minecraft_orange_rn"}, {"Y": 2, "X": 2, "Z": 2, "Type": "cwc_minecraft_orange_rn"}, {"Y": 3, "X": 2, "Z": 0, "Type": "cwc_minecraft_yellow_rn"}, {"Y": 3, "X": 2, "Z": 1, "Type": "cwc_minecraft_yellow_rn"}, {"Y": 3, "X": 2, "Z": 2, "Type": "cwc_minecraft_yellow_rn"}, {"Y": 4, "X": 2, "Z": 0, "Type": "cwc_minecraft_yellow_rn"}, {"Y": 4, "X": 2, "Z": 1, "Type": "cwc_minecraft_yellow_rn"}, {"Y": 4, "X": 2, "Z": 2, "Type": "cwc_minecraft_yellow_rn"}], "XPos": -0.09659625826361874, "TimeAlive": 7961, "ZPos": -3.407726419682822, "Timestamp": "2018-04-09 20:30:31", "Yaw": -14.4002075, "YPos": 3.492745412442804, "BuilderGridRelative": [{"Y": -2, "X": 1, "Z": 4, "Type": "cwc_minecraft_yellow_rn"}, {"Y": -2, "X": 3, "Z": 4, "Type": "cwc_minecraft_yellow_rn"}, {"Y": -2, "X": 1, "Z": 6, "Type": "cwc_minecraft_yellow_rn"}, {"Y": -2, "X": 3, "Z": 6, "Type": "cwc_minecraft_yellow_rn"}, {"Y": -1, "X": 1, "Z": 4, "Type": "cwc_minecraft_orange_rn"}, {"Y": -1, "X": 2, "Z": 4, "Type": "cwc_minecraft_orange_rn"}, {"Y": -1, "X": 3, "Z": 4, "Type": "cwc_minecraft_orange_rn"}, {"Y": -1, "X": 1, "Z": 5, "Type": "cwc_minecraft_orange_rn"}, {"Y": -1, "X": 2, "Z": 5, "Type": "cwc_minecraft_orange_rn"}, {"Y": -1, "X": 3, "Z": 5, "Type": "cwc_minecraft_orange_rn"}, {"Y": -1, "X": 1, "Z": 6, "Type": "cwc_minecraft_orange_rn"}, {"Y": -1, "X": 2, "Z": 6, "Type": "cwc_minecraft_orange_rn"}, {"Y": -1, "X": 3, "Z": 6, "Type": "cwc_minecraft_orange_rn"}, {"Y": 0, "X": 3, "Z": 4, "Type": "cwc_minecraft_yellow_rn"}, {"Y": 0, "X": 3, "Z": 5, "Type": "cwc_minecraft_yellow_rn"}, {"Y": 0, "X": 3, "Z": 6, "Type": "cwc_minecraft_yellow_rn"}, {"Y": 1, "X": 3, "Z": 4, "Type": "cwc_minecraft_yellow_rn"}, {"Y": 1, "X": 3, "Z": 5, "Type": "cwc_minecraft_yellow_rn"}, {"Y": 1, "X": 3, "Z": 6, "Type": "cwc_minecraft_yellow_rn"}], "DistanceTravelled": 4735, "BuilderInventory": [{"Index": 0, "Type": "cwc_minecraft_red_rn", "Quantity": 20}, {"Index": 1, "Type": "cwc_minecraft_orange_rn", "Quantity": 11}, {"Index": 2, "Type": "cwc_minecraft_yellow_rn", "Quantity": 10}, {"Index": 3, "Type": "cwc_minecraft_green_rn", "Quantity": 20}, {"Index": 4, "Type": "cwc_minecraft_blue_rn", "Quantity": 20}, {"Index": 5, "Type": "cwc_minecraft_purple_rn", "Quantity": 20}], "Pitch": 36.149952}], "NumFixedViewers": 4, "TimeElapsed": 408.72316908836365}